{
"meta":{"test_sets":[],"test_metrics":[],"learn_metrics":[{"best_value":"Min","name":"RMSE"}],"launch_mode":"Train","parameters":"","iteration_count":1000,"learn_sets":["learn"],"name":"experiment"},
"iterations":[
{"learn":[14.61268541],"iteration":0,"passed_time":0.1348412206,"remaining_time":134.7063794},
{"learn":[14.23196558],"iteration":1,"passed_time":0.1362662987,"remaining_time":67.99688306},
{"learn":[13.86674177],"iteration":2,"passed_time":0.1371955272,"remaining_time":45.59464686},
{"learn":[13.49946468],"iteration":3,"passed_time":0.1390674936,"remaining_time":34.62780591},
{"learn":[13.16661202],"iteration":4,"passed_time":0.1407316121,"remaining_time":28.00559081},
{"learn":[12.85632158],"iteration":5,"passed_time":0.1431584186,"remaining_time":23.71657801},
{"learn":[12.56784336],"iteration":6,"passed_time":0.1451975439,"remaining_time":20.59730873},
{"learn":[12.31617801],"iteration":7,"passed_time":0.1481898003,"remaining_time":18.37553524},
{"learn":[12.01509946],"iteration":8,"passed_time":0.1506151873,"remaining_time":16.58440562},
{"learn":[11.71512571],"iteration":9,"passed_time":0.1530045835,"remaining_time":15.14745376},
{"learn":[11.43264457],"iteration":10,"passed_time":0.1557840213,"remaining_time":14.00639973},
{"learn":[11.17973129],"iteration":11,"passed_time":0.1587528057,"remaining_time":13.07064767},
{"learn":[10.93746433],"iteration":12,"passed_time":0.1607054906,"remaining_time":12.20125532},
{"learn":[10.69387075],"iteration":13,"passed_time":0.1629785737,"remaining_time":11.47834812},
{"learn":[10.4615922],"iteration":14,"passed_time":0.1652136252,"remaining_time":10.84902805},
{"learn":[10.2299235],"iteration":15,"passed_time":0.1674575905,"remaining_time":10.29864181},
{"learn":[10.01419731],"iteration":16,"passed_time":0.1697161232,"remaining_time":9.813585239},
{"learn":[9.795856918],"iteration":17,"passed_time":0.1719335675,"remaining_time":9.379931295},
{"learn":[9.60040151],"iteration":18,"passed_time":0.174024603,"remaining_time":8.98516503},
{"learn":[9.418664989],"iteration":19,"passed_time":0.1763651659,"remaining_time":8.641893131},
{"learn":[9.249278645],"iteration":20,"passed_time":0.1785641554,"remaining_time":8.324490862},
{"learn":[9.090113396],"iteration":21,"passed_time":0.1808956339,"remaining_time":8.04163318},
{"learn":[8.909548708],"iteration":22,"passed_time":0.1834641303,"remaining_time":7.793237189},
{"learn":[8.740140208],"iteration":23,"passed_time":0.1852307727,"remaining_time":7.532718088},
{"learn":[8.59377682],"iteration":24,"passed_time":0.1874102918,"remaining_time":7.309001382},
{"learn":[8.453885414],"iteration":25,"passed_time":0.1901550583,"remaining_time":7.123501032},
{"learn":[8.317732234],"iteration":26,"passed_time":0.193703957,"remaining_time":6.980516674},
{"learn":[8.180896085],"iteration":27,"passed_time":0.1964152243,"remaining_time":6.818414213},
{"learn":[8.053220863],"iteration":28,"passed_time":0.1990113397,"remaining_time":6.66344865},
{"learn":[7.924234474],"iteration":29,"passed_time":0.2017560756,"remaining_time":6.523446443},
{"learn":[7.818879511],"iteration":30,"passed_time":0.2042958526,"remaining_time":6.385892942},
{"learn":[7.719346395],"iteration":31,"passed_time":0.2069139727,"remaining_time":6.259147674},
{"learn":[7.624163594],"iteration":32,"passed_time":0.2092709573,"remaining_time":6.132273204},
{"learn":[7.524952543],"iteration":33,"passed_time":0.2115803282,"remaining_time":6.0113705},
{"learn":[7.424464745],"iteration":34,"passed_time":0.2145451997,"remaining_time":5.915317649},
{"learn":[7.327482321],"iteration":35,"passed_time":0.2165795642,"remaining_time":5.799519443},
{"learn":[7.238666841],"iteration":36,"passed_time":0.2184741028,"remaining_time":5.686231377},
{"learn":[7.158842395],"iteration":37,"passed_time":0.2206666606,"remaining_time":5.586350723},
{"learn":[7.074348246],"iteration":38,"passed_time":0.2228737084,"remaining_time":5.491836762},
{"learn":[6.992269093],"iteration":39,"passed_time":0.2248393717,"remaining_time":5.396144921},
{"learn":[6.925219745],"iteration":40,"passed_time":0.226599628,"remaining_time":5.300220568},
{"learn":[6.86013671],"iteration":41,"passed_time":0.228831057,"remaining_time":5.219527443},
{"learn":[6.786739622],"iteration":42,"passed_time":0.2308327836,"remaining_time":5.137371485},
{"learn":[6.73057926],"iteration":43,"passed_time":0.2327440763,"remaining_time":5.056894022},
{"learn":[6.666356486],"iteration":44,"passed_time":0.2347069781,"remaining_time":4.981003646},
{"learn":[6.606182832],"iteration":45,"passed_time":0.2367136922,"remaining_time":4.909236138},
{"learn":[6.547854615],"iteration":46,"passed_time":0.2388474819,"remaining_time":4.843013834},
{"learn":[6.49240675],"iteration":47,"passed_time":0.240195646,"remaining_time":4.763880312},
{"learn":[6.431317261],"iteration":48,"passed_time":0.241319632,"remaining_time":4.683570817},
{"learn":[6.377586395],"iteration":49,"passed_time":0.2421404403,"remaining_time":4.600668366},
{"learn":[6.327558015],"iteration":50,"passed_time":0.2433967071,"remaining_time":4.529087745},
{"learn":[6.282040317],"iteration":51,"passed_time":0.2456127212,"remaining_time":4.47770884},
{"learn":[6.237655841],"iteration":52,"passed_time":0.248313529,"remaining_time":4.436847395},
{"learn":[6.192792003],"iteration":53,"passed_time":0.2496944101,"remaining_time":4.374276146},
{"learn":[6.150579347],"iteration":54,"passed_time":0.2518776452,"remaining_time":4.327715904},
{"learn":[6.115693845],"iteration":55,"passed_time":0.2536331553,"remaining_time":4.275530333},
{"learn":[6.078780782],"iteration":56,"passed_time":0.2558401119,"remaining_time":4.232582904},
{"learn":[6.045146957],"iteration":57,"passed_time":0.2578595666,"remaining_time":4.18799503},
{"learn":[6.008080327],"iteration":58,"passed_time":0.2587713298,"remaining_time":4.127183412},
{"learn":[5.977575734],"iteration":59,"passed_time":0.2596060908,"remaining_time":4.06716209},
{"learn":[5.948036502],"iteration":60,"passed_time":0.2610444206,"remaining_time":4.01837231},
{"learn":[5.914888282],"iteration":61,"passed_time":0.2631187355,"remaining_time":3.980731838},
{"learn":[5.884957796],"iteration":62,"passed_time":0.265154759,"remaining_time":3.94365094},
{"learn":[5.849539885],"iteration":63,"passed_time":0.2671269563,"remaining_time":3.906731736},
{"learn":[5.821387627],"iteration":64,"passed_time":0.2689646545,"remaining_time":3.868953107},
{"learn":[5.797012279],"iteration":65,"passed_time":0.2707100738,"remaining_time":3.830957711},
{"learn":[5.768685095],"iteration":66,"passed_time":0.2726482461,"remaining_time":3.796728561},
{"learn":[5.755484587],"iteration":67,"passed_time":0.2736121861,"remaining_time":3.750096433},
{"learn":[5.731887055],"iteration":68,"passed_time":0.2754579377,"remaining_time":3.716686087},
{"learn":[5.707148487],"iteration":69,"passed_time":0.277463953,"remaining_time":3.686306804},
{"learn":[5.685365039],"iteration":70,"passed_time":0.2794943307,"remaining_time":3.657045538},
{"learn":[5.663541834],"iteration":71,"passed_time":0.2817261409,"remaining_time":3.631136927},
{"learn":[5.638108797],"iteration":72,"passed_time":0.284129478,"remaining_time":3.608055152},
{"learn":[5.619204893],"iteration":73,"passed_time":0.2869520975,"remaining_time":3.59077895},
{"learn":[5.598472793],"iteration":74,"passed_time":0.2893374942,"remaining_time":3.568495762},
{"learn":[5.577007075],"iteration":75,"passed_time":0.2913432195,"remaining_time":3.542120194},
{"learn":[5.562637084],"iteration":76,"passed_time":0.2932478883,"remaining_time":3.515166245},
{"learn":[5.54729991],"iteration":77,"passed_time":0.2951583948,"remaining_time":3.48892359},
{"learn":[5.530737623],"iteration":78,"passed_time":0.296790604,"remaining_time":3.460052485},
{"learn":[5.513704873],"iteration":79,"passed_time":0.2985163837,"remaining_time":3.432938413},
{"learn":[5.501575529],"iteration":80,"passed_time":0.3003574933,"remaining_time":3.407759708},
{"learn":[5.484080734],"iteration":81,"passed_time":0.3016718087,"remaining_time":3.377252688},
{"learn":[5.472178894],"iteration":82,"passed_time":0.3031445393,"remaining_time":3.349199307},
{"learn":[5.458923342],"iteration":83,"passed_time":0.3044339724,"remaining_time":3.319779984},
{"learn":[5.451382371],"iteration":84,"passed_time":0.3053564838,"remaining_time":3.287072738},
{"learn":[5.441410748],"iteration":85,"passed_time":0.3066374436,"remaining_time":3.258914227},
{"learn":[5.434047468],"iteration":86,"passed_time":0.3075513033,"remaining_time":3.227521148},
{"learn":[5.422107497],"iteration":87,"passed_time":0.3087764772,"remaining_time":3.200047127},
{"learn":[5.40731265],"iteration":88,"passed_time":0.3102204316,"remaining_time":3.175402396},
{"learn":[5.396360181],"iteration":89,"passed_time":0.31163592,"remaining_time":3.150985413},
{"learn":[5.383793239],"iteration":90,"passed_time":0.313222851,"remaining_time":3.1287865},
{"learn":[5.369605034],"iteration":91,"passed_time":0.3144701456,"remaining_time":3.103683611},
{"learn":[5.357467333],"iteration":92,"passed_time":0.3157353033,"remaining_time":3.079267958},
{"learn":[5.341109968],"iteration":93,"passed_time":0.3169875119,"remaining_time":3.055220062},
{"learn":[5.330529276],"iteration":94,"passed_time":0.3181438716,"remaining_time":3.030738987},
{"learn":[5.319862075],"iteration":95,"passed_time":0.3193537345,"remaining_time":3.007247667},
{"learn":[5.313052243],"iteration":96,"passed_time":0.3209837132,"remaining_time":2.988126732},
{"learn":[5.299677207],"iteration":97,"passed_time":0.322322442,"remaining_time":2.966682068},
{"learn":[5.287546698],"iteration":98,"passed_time":0.3235016756,"remaining_time":2.944192017},
{"learn":[5.279803754],"iteration":99,"passed_time":0.3246469866,"remaining_time":2.92182288},
{"learn":[5.272254612],"iteration":100,"passed_time":0.3257066507,"remaining_time":2.899111673},
{"learn":[5.268813888],"iteration":101,"passed_time":0.3262222705,"remaining_time":2.872035283},
{"learn":[5.258113767],"iteration":102,"passed_time":0.3272700177,"remaining_time":2.850108795},
{"learn":[5.251018576],"iteration":103,"passed_time":0.328212284,"remaining_time":2.827675062},
{"learn":[5.24171237],"iteration":104,"passed_time":0.3291629532,"remaining_time":2.805722315},
{"learn":[5.233984943],"iteration":105,"passed_time":0.3300003141,"remaining_time":2.783210197},
{"learn":[5.226240449],"iteration":106,"passed_time":0.3307681142,"remaining_time":2.760522673},
{"learn":[5.220541644],"iteration":107,"passed_time":0.3315593242,"remaining_time":2.738434418},
{"learn":[5.211712096],"iteration":108,"passed_time":0.3324476613,"remaining_time":2.717530883},
{"learn":[5.203388597],"iteration":109,"passed_time":0.3332232419,"remaining_time":2.696078958},
{"learn":[5.196026544],"iteration":110,"passed_time":0.333955647,"remaining_time":2.674653785},
{"learn":[5.188716772],"iteration":111,"passed_time":0.3346665983,"remaining_time":2.65342803},
{"learn":[5.182163132],"iteration":112,"passed_time":0.3353309213,"remaining_time":2.632199356},
{"learn":[5.17764747],"iteration":113,"passed_time":0.3359316824,"remaining_time":2.610837462},
{"learn":[5.170548056],"iteration":114,"passed_time":0.336630461,"remaining_time":2.590590939},
{"learn":[5.165901827],"iteration":115,"passed_time":0.3371646714,"remaining_time":2.569427324},
{"learn":[5.160333668],"iteration":116,"passed_time":0.337889674,"remaining_time":2.550056258},
{"learn":[5.148953243],"iteration":117,"passed_time":0.3385840527,"remaining_time":2.530772326},
{"learn":[5.144729126],"iteration":118,"passed_time":0.339053163,"remaining_time":2.510133081},
{"learn":[5.139939946],"iteration":119,"passed_time":0.3396781788,"remaining_time":2.490973312},
{"learn":[5.132898872],"iteration":120,"passed_time":0.3402850106,"remaining_time":2.471987804},
{"learn":[5.129073077],"iteration":121,"passed_time":0.3409680472,"remaining_time":2.453852012},
{"learn":[5.127123916],"iteration":122,"passed_time":0.3413674521,"remaining_time":2.433977687},
{"learn":[5.121282057],"iteration":123,"passed_time":0.3420318601,"remaining_time":2.416289592},
{"learn":[5.114489821],"iteration":124,"passed_time":0.3426220453,"remaining_time":2.398354317},
{"learn":[5.107777291],"iteration":125,"passed_time":0.3432491891,"remaining_time":2.380950724},
{"learn":[5.103518754],"iteration":126,"passed_time":0.3438778535,"remaining_time":2.36382178},
{"learn":[5.101133351],"iteration":127,"passed_time":0.3443239177,"remaining_time":2.34570669},
{"learn":[5.096462705],"iteration":128,"passed_time":0.3451151086,"remaining_time":2.330195811},
{"learn":[5.08562082],"iteration":129,"passed_time":0.3458756537,"remaining_time":2.314706298},
{"learn":[5.080483682],"iteration":130,"passed_time":0.3466688192,"remaining_time":2.299658045},
{"learn":[5.07437499],"iteration":131,"passed_time":0.3473994895,"remaining_time":2.284414825},
{"learn":[5.070683732],"iteration":132,"passed_time":0.3480895879,"remaining_time":2.269125358},
{"learn":[5.06432037],"iteration":133,"passed_time":0.3488295712,"remaining_time":2.254376184},
{"learn":[5.057436484],"iteration":134,"passed_time":0.3494685172,"remaining_time":2.239187166},
{"learn":[5.053254656],"iteration":135,"passed_time":0.3501803682,"remaining_time":2.22467528},
{"learn":[5.04801663],"iteration":136,"passed_time":0.3508575252,"remaining_time":2.210146309},
{"learn":[5.045680836],"iteration":137,"passed_time":0.3514286268,"remaining_time":2.195155625},
{"learn":[5.041857933],"iteration":138,"passed_time":0.3521022805,"remaining_time":2.181007651},
{"learn":[5.035264888],"iteration":139,"passed_time":0.3527946083,"remaining_time":2.16716688},
{"learn":[5.028771948],"iteration":140,"passed_time":0.3534447712,"remaining_time":2.153255734},
{"learn":[5.024912247],"iteration":141,"passed_time":0.3540920573,"remaining_time":2.13951398},
{"learn":[5.02239068],"iteration":142,"passed_time":0.3547279406,"remaining_time":2.125887028},
{"learn":[5.017110572],"iteration":143,"passed_time":0.3553957577,"remaining_time":2.112630337},
{"learn":[5.010707886],"iteration":144,"passed_time":0.3561309397,"remaining_time":2.099944506},
{"learn":[5.004389868],"iteration":145,"passed_time":0.3569471673,"remaining_time":2.087896444},
{"learn":[4.997628683],"iteration":146,"passed_time":0.3576592297,"remaining_time":2.075396755},
{"learn":[4.991497851],"iteration":147,"passed_time":0.3583338213,"remaining_time":2.062840647},
{"learn":[4.988345253],"iteration":148,"passed_time":0.3589484402,"remaining_time":2.050101494},
{"learn":[4.98460423],"iteration":149,"passed_time":0.3595307636,"remaining_time":2.037340994},
{"learn":[4.982441783],"iteration":150,"passed_time":0.3601243747,"remaining_time":2.024805259},
{"learn":[4.977461771],"iteration":151,"passed_time":0.3607045419,"remaining_time":2.012351655},
{"learn":[4.973601586],"iteration":152,"passed_time":0.3612800049,"remaining_time":2.000027217},
{"learn":[4.968328804],"iteration":153,"passed_time":0.3618833246,"remaining_time":1.988008393},
{"learn":[4.9640736],"iteration":154,"passed_time":0.3624212954,"remaining_time":1.97578061},
{"learn":[4.960865882],"iteration":155,"passed_time":0.3630329895,"remaining_time":1.964101558},
{"learn":[4.957014156],"iteration":156,"passed_time":0.3636458084,"remaining_time":1.952569532},
{"learn":[4.952244852],"iteration":157,"passed_time":0.3642873574,"remaining_time":1.941328829},
{"learn":[4.949695675],"iteration":158,"passed_time":0.3648710042,"remaining_time":1.929915186},
{"learn":[4.946584698],"iteration":159,"passed_time":0.3654848093,"remaining_time":1.918795249},
{"learn":[4.940192834],"iteration":160,"passed_time":0.3660863182,"remaining_time":1.907741745},
{"learn":[4.936727994],"iteration":161,"passed_time":0.3666329639,"remaining_time":1.89653348},
{"learn":[4.932342063],"iteration":162,"passed_time":0.3672042248,"remaining_time":1.88558243},
{"learn":[4.925830838],"iteration":163,"passed_time":0.3677816035,"remaining_time":1.87478915},
{"learn":[4.922571773],"iteration":164,"passed_time":0.3683711474,"remaining_time":1.864181261},
{"learn":[4.918395814],"iteration":165,"passed_time":0.3689652734,"remaining_time":1.853717097},
{"learn":[4.911142452],"iteration":166,"passed_time":0.369580372,"remaining_time":1.843475748},
{"learn":[4.908276131],"iteration":167,"passed_time":0.3702162768,"remaining_time":1.833452037},
{"learn":[4.904584645],"iteration":168,"passed_time":0.370802141,"remaining_time":1.823293368},
{"learn":[4.89795517],"iteration":169,"passed_time":0.3714084215,"remaining_time":1.813346999},
{"learn":[4.895556491],"iteration":170,"passed_time":0.3720162107,"remaining_time":1.803517185},
{"learn":[4.890591233],"iteration":171,"passed_time":0.3725953541,"remaining_time":1.793656705},
{"learn":[4.884629277],"iteration":172,"passed_time":0.3731780246,"remaining_time":1.783920384},
{"learn":[4.880550786],"iteration":173,"passed_time":0.3737755085,"remaining_time":1.774359598},
{"learn":[4.876384842],"iteration":174,"passed_time":0.3743342089,"remaining_time":1.764718413},
{"learn":[4.872638238],"iteration":175,"passed_time":0.3749494262,"remaining_time":1.755445041},
{"learn":[4.869137118],"iteration":176,"passed_time":0.3755506624,"remaining_time":1.746204492},
{"learn":[4.863587157],"iteration":177,"passed_time":0.3763804347,"remaining_time":1.73811639},
{"learn":[4.858028614],"iteration":178,"passed_time":0.3770287483,"remaining_time":1.729277108},
{"learn":[4.853838176],"iteration":179,"passed_time":0.3776581399,"remaining_time":1.720442637},
{"learn":[4.853462329],"iteration":180,"passed_time":0.3779726621,"remaining_time":1.71027409},
{"learn":[4.851573196],"iteration":181,"passed_time":0.378555754,"remaining_time":1.701420916},
{"learn":[4.848442087],"iteration":182,"passed_time":0.3791767566,"remaining_time":1.692827378},
{"learn":[4.845547104],"iteration":183,"passed_time":0.3797783752,"remaining_time":1.684234533},
{"learn":[4.839868817],"iteration":184,"passed_time":0.3803579538,"remaining_time":1.675630986},
{"learn":[4.836336958],"iteration":185,"passed_time":0.3809337908,"remaining_time":1.667097343},
{"learn":[4.831124789],"iteration":186,"passed_time":0.3815040556,"remaining_time":1.658624584},
{"learn":[4.827407333],"iteration":187,"passed_time":0.3821762243,"remaining_time":1.650676033},
{"learn":[4.824088918],"iteration":188,"passed_time":0.3828661748,"remaining_time":1.642880782},
{"learn":[4.820934539],"iteration":189,"passed_time":0.3835061913,"remaining_time":1.634947447},
{"learn":[4.816975227],"iteration":190,"passed_time":0.3840909576,"remaining_time":1.626856464},
{"learn":[4.812340486],"iteration":191,"passed_time":0.3847167132,"remaining_time":1.619016168},
{"learn":[4.806402747],"iteration":192,"passed_time":0.3852929801,"remaining_time":1.611043704},
{"learn":[4.801521788],"iteration":193,"passed_time":0.3858661567,"remaining_time":1.603134651},
{"learn":[4.797601172],"iteration":194,"passed_time":0.3864831111,"remaining_time":1.595481561},
{"learn":[4.792694629],"iteration":195,"passed_time":0.3870964082,"remaining_time":1.587885266},
{"learn":[4.789794613],"iteration":196,"passed_time":0.3877111014,"remaining_time":1.580365556},
{"learn":[4.785367055],"iteration":197,"passed_time":0.3883290677,"remaining_time":1.57292885},
{"learn":[4.780376856],"iteration":198,"passed_time":0.3890597586,"remaining_time":1.566014405},
{"learn":[4.776691261],"iteration":199,"passed_time":0.3897088599,"remaining_time":1.55883544},
{"learn":[4.773470753],"iteration":200,"passed_time":0.3903036281,"remaining_time":1.551505467},
{"learn":[4.77207327],"iteration":201,"passed_time":0.3909008154,"remaining_time":1.544251736},
{"learn":[4.767347177],"iteration":202,"passed_time":0.3914826645,"remaining_time":1.537003367},
{"learn":[4.763983068],"iteration":203,"passed_time":0.3920910989,"remaining_time":1.529924092},
{"learn":[4.761588849],"iteration":204,"passed_time":0.3926662355,"remaining_time":1.522778816},
{"learn":[4.758558086],"iteration":205,"passed_time":0.3932125777,"remaining_time":1.515586343},
{"learn":[4.753678804],"iteration":206,"passed_time":0.3937824325,"remaining_time":1.508548159},
{"learn":[4.746510889],"iteration":207,"passed_time":0.3944217253,"remaining_time":1.50183657},
{"learn":[4.744840601],"iteration":208,"passed_time":0.3951746316,"remaining_time":1.495613079},
{"learn":[4.741702222],"iteration":209,"passed_time":0.3958078434,"remaining_time":1.488991411},
{"learn":[4.739352853],"iteration":210,"passed_time":0.3964277931,"remaining_time":1.482376914},
{"learn":[4.735539287],"iteration":211,"passed_time":0.3970328476,"remaining_time":1.475763603},
{"learn":[4.730726751],"iteration":212,"passed_time":0.3976269851,"remaining_time":1.469166372},
{"learn":[4.726416092],"iteration":213,"passed_time":0.3982094189,"remaining_time":1.462582258},
{"learn":[4.721293082],"iteration":214,"passed_time":0.3987937636,"remaining_time":1.456060951},
{"learn":[4.718443695],"iteration":215,"passed_time":0.3993928727,"remaining_time":1.449648205},
{"learn":[4.711627962],"iteration":216,"passed_time":0.3999854693,"remaining_time":1.443265541},
{"learn":[4.709790764],"iteration":217,"passed_time":0.4005885974,"remaining_time":1.436973776},
{"learn":[4.706913073],"iteration":218,"passed_time":0.401258183,"remaining_time":1.430970963},
{"learn":[4.703846389],"iteration":219,"passed_time":0.4018989091,"remaining_time":1.424914314},
{"learn":[4.701001135],"iteration":220,"passed_time":0.4025228415,"remaining_time":1.418847482},
{"learn":[4.700380864],"iteration":221,"passed_time":0.4031190303,"remaining_time":1.412732458},
{"learn":[4.695837486],"iteration":222,"passed_time":0.4037304347,"remaining_time":1.406719945},
{"learn":[4.691242996],"iteration":223,"passed_time":0.4042896501,"remaining_time":1.400574859},
{"learn":[4.690284609],"iteration":224,"passed_time":0.4048908058,"remaining_time":1.394623887},
{"learn":[4.68827119],"iteration":225,"passed_time":0.4055336912,"remaining_time":1.388863172},
{"learn":[4.686922425],"iteration":226,"passed_time":0.4061533697,"remaining_time":1.383068523},
{"learn":[4.686085874],"iteration":227,"passed_time":0.4067396209,"remaining_time":1.377206085},
{"learn":[4.683230741],"iteration":228,"passed_time":0.4073540524,"remaining_time":1.371484604},
{"learn":[4.6773487],"iteration":229,"passed_time":0.408149224,"remaining_time":1.366412619},
{"learn":[4.671462906],"iteration":230,"passed_time":0.4087807496,"remaining_time":1.360832885},
{"learn":[4.664799601],"iteration":231,"passed_time":0.4094150054,"remaining_time":1.355304845},
{"learn":[4.660979386],"iteration":232,"passed_time":0.4099938913,"remaining_time":1.349636544},
{"learn":[4.656281279],"iteration":233,"passed_time":0.410589907,"remaining_time":1.344067815},
{"learn":[4.651997094],"iteration":234,"passed_time":0.4111873977,"remaining_time":1.33854621},
{"learn":[4.650151977],"iteration":235,"passed_time":0.4118000557,"remaining_time":1.333115435},
{"learn":[4.648478046],"iteration":236,"passed_time":0.4123448532,"remaining_time":1.327506848},
{"learn":[4.646364602],"iteration":237,"passed_time":0.4129170259,"remaining_time":1.322028461},
{"learn":[4.642635873],"iteration":238,"passed_time":0.4135362424,"remaining_time":1.316740922},
{"learn":[4.640860821],"iteration":239,"passed_time":0.4141574028,"remaining_time":1.311498442},
{"learn":[4.639446822],"iteration":240,"passed_time":0.4149087333,"remaining_time":1.306704268},
{"learn":[4.637120072],"iteration":241,"passed_time":0.4155992903,"remaining_time":1.301753149},
{"learn":[4.633769267],"iteration":242,"passed_time":0.4162935414,"remaining_time":1.296848604},
{"learn":[4.630491517],"iteration":243,"passed_time":0.4169508374,"remaining_time":1.29186407},
{"learn":[4.627813333],"iteration":244,"passed_time":0.417680872,"remaining_time":1.287139014},
{"learn":[4.622496304],"iteration":245,"passed_time":0.4183363486,"remaining_time":1.282217914},
{"learn":[4.618979301],"iteration":246,"passed_time":0.4190151316,"remaining_time":1.277402405},
{"learn":[4.616563458],"iteration":247,"passed_time":0.4196532624,"remaining_time":1.272496989},
{"learn":[4.614759385],"iteration":248,"passed_time":0.4204173783,"remaining_time":1.268005828},
{"learn":[4.61251363],"iteration":249,"passed_time":0.4210615291,"remaining_time":1.263184587},
{"learn":[4.608796693],"iteration":250,"passed_time":0.4217779815,"remaining_time":1.258612383},
{"learn":[4.60847774],"iteration":251,"passed_time":0.422405498,"remaining_time":1.253806796},
{"learn":[4.605195659],"iteration":252,"passed_time":0.4230266715,"remaining_time":1.249015508},
{"learn":[4.60103766],"iteration":253,"passed_time":0.4236427868,"remaining_time":1.244242201},
{"learn":[4.599325598],"iteration":254,"passed_time":0.4242007739,"remaining_time":1.239331673},
{"learn":[4.597012808],"iteration":255,"passed_time":0.4247706463,"remaining_time":1.234489691},
{"learn":[4.594161533],"iteration":256,"passed_time":0.4253560746,"remaining_time":1.229725928},
{"learn":[4.592197259],"iteration":257,"passed_time":0.4259179389,"remaining_time":1.224926785},
{"learn":[4.58952828],"iteration":258,"passed_time":0.426600626,"remaining_time":1.220506038},
{"learn":[4.585816572],"iteration":259,"passed_time":0.4273124065,"remaining_time":1.216196849},
{"learn":[4.582934052],"iteration":260,"passed_time":0.4279785635,"remaining_time":1.211786048},
{"learn":[4.582234842],"iteration":261,"passed_time":0.4285489486,"remaining_time":1.207134061},
{"learn":[4.57571562],"iteration":262,"passed_time":0.4291512257,"remaining_time":1.202602484},
{"learn":[4.571197349],"iteration":263,"passed_time":0.4297950659,"remaining_time":1.198216547},
{"learn":[4.56723703],"iteration":264,"passed_time":0.4303949803,"remaining_time":1.193737021},
{"learn":[4.560335567],"iteration":265,"passed_time":0.4310304996,"remaining_time":1.189384912},
{"learn":[4.554709345],"iteration":266,"passed_time":0.4316308492,"remaining_time":1.184964092},
{"learn":[4.552806306],"iteration":267,"passed_time":0.4322125941,"remaining_time":1.180520966},
{"learn":[4.550766241],"iteration":268,"passed_time":0.4329333919,"remaining_time":1.176484422},
{"learn":[4.549216045],"iteration":269,"passed_time":0.4336232841,"remaining_time":1.172388879},
{"learn":[4.547687452],"iteration":270,"passed_time":0.4343379357,"remaining_time":1.168385074},
{"learn":[4.545642435],"iteration":271,"passed_time":0.434974219,"remaining_time":1.164195704},
{"learn":[4.543930359],"iteration":272,"passed_time":0.4356129582,"remaining_time":1.160038903},
{"learn":[4.541029943],"iteration":273,"passed_time":0.4362256101,"remaining_time":1.15583866},
{"learn":[4.537781449],"iteration":274,"passed_time":0.4368080446,"remaining_time":1.151584845},
{"learn":[4.53066128],"iteration":275,"passed_time":0.4373813123,"remaining_time":1.147333587},
{"learn":[4.526763956],"iteration":276,"passed_time":0.4379367186,"remaining_time":1.143062266},
{"learn":[4.522036004],"iteration":277,"passed_time":0.4385592775,"remaining_time":1.13899208},
{"learn":[4.515307629],"iteration":278,"passed_time":0.4392187355,"remaining_time":1.135041965},
{"learn":[4.51109143],"iteration":279,"passed_time":0.4403910272,"remaining_time":1.13243407},
{"learn":[4.508233494],"iteration":280,"passed_time":0.4411489571,"remaining_time":1.128776157},
{"learn":[4.502555629],"iteration":281,"passed_time":0.4418405474,"remaining_time":1.124969904},
{"learn":[4.500081355],"iteration":282,"passed_time":0.4426366707,"remaining_time":1.121450505},
{"learn":[4.495281743],"iteration":283,"passed_time":0.4433618422,"remaining_time":1.117771405},
{"learn":[4.492138869],"iteration":284,"passed_time":0.4439810058,"remaining_time":1.113847085},
{"learn":[4.491708261],"iteration":285,"passed_time":0.444557737,"remaining_time":1.109839945},
{"learn":[4.489398865],"iteration":286,"passed_time":0.4451380796,"remaining_time":1.105865682},
{"learn":[4.485796373],"iteration":287,"passed_time":0.4458080435,"remaining_time":1.102136552},
{"learn":[4.479542205],"iteration":288,"passed_time":0.4464485619,"remaining_time":1.09835615},
{"learn":[4.475986993],"iteration":289,"passed_time":0.4471420034,"remaining_time":1.094726974},
{"learn":[4.468661855],"iteration":290,"passed_time":0.4477936701,"remaining_time":1.091016193},
{"learn":[4.463785664],"iteration":291,"passed_time":0.4484780894,"remaining_time":1.087405778},
{"learn":[4.460445831],"iteration":292,"passed_time":0.4491567893,"remaining_time":1.083801536},
{"learn":[4.45692492],"iteration":293,"passed_time":0.4500021209,"remaining_time":1.080617338},
{"learn":[4.454031688],"iteration":294,"passed_time":0.4507437667,"remaining_time":1.077201205},
{"learn":[4.451672391],"iteration":295,"passed_time":0.4513640781,"remaining_time":1.073514564},
{"learn":[4.45031553],"iteration":296,"passed_time":0.4520652857,"remaining_time":1.070040053},
{"learn":[4.446782666],"iteration":297,"passed_time":0.4526792893,"remaining_time":1.066378728},
{"learn":[4.444369689],"iteration":298,"passed_time":0.4532703365,"remaining_time":1.062683966},
{"learn":[4.44411683],"iteration":299,"passed_time":0.4538189989,"remaining_time":1.058910998},
{"learn":[4.440876943],"iteration":300,"passed_time":0.4544231201,"remaining_time":1.055288242},
{"learn":[4.439336453],"iteration":301,"passed_time":0.4549866058,"remaining_time":1.051591559},
{"learn":[4.436666901],"iteration":302,"passed_time":0.4555482126,"remaining_time":1.047911235},
{"learn":[4.433043336],"iteration":303,"passed_time":0.4561449394,"remaining_time":1.044331835},
{"learn":[4.431419305],"iteration":304,"passed_time":0.4567390501,"remaining_time":1.040766032},
{"learn":[4.428859646],"iteration":305,"passed_time":0.4573710968,"remaining_time":1.03730569},
{"learn":[4.424552441],"iteration":306,"passed_time":0.4580311816,"remaining_time":1.033927065},
{"learn":[4.422706391],"iteration":307,"passed_time":0.458609948,"remaining_time":1.03038339},
{"learn":[4.421427994],"iteration":308,"passed_time":0.4592073376,"remaining_time":1.026900551},
{"learn":[4.418733158],"iteration":309,"passed_time":0.4598099852,"remaining_time":1.023448032},
{"learn":[4.415656941],"iteration":310,"passed_time":0.4604065526,"remaining_time":1.020000369},
{"learn":[4.410747417],"iteration":311,"passed_time":0.4610371541,"remaining_time":1.016646032},
{"learn":[4.408126521],"iteration":312,"passed_time":0.4616386293,"remaining_time":1.01324517},
{"learn":[4.407843853],"iteration":313,"passed_time":0.462184947,"remaining_time":1.009741636},
{"learn":[4.405219398],"iteration":314,"passed_time":0.4627676972,"remaining_time":1.006336103},
{"learn":[4.402708465],"iteration":315,"passed_time":0.4633824011,"remaining_time":1.003017602},
{"learn":[4.40104971],"iteration":316,"passed_time":0.4640277136,"remaining_time":0.9997821086},
{"learn":[4.400830038],"iteration":317,"passed_time":0.4648219538,"remaining_time":0.9968823035},
{"learn":[4.39784288],"iteration":318,"passed_time":0.4655070141,"remaining_time":0.9937626225},
{"learn":[4.393741845],"iteration":319,"passed_time":0.466159362,"remaining_time":0.9905886442},
{"learn":[4.393425936],"iteration":320,"passed_time":0.4668489972,"remaining_time":0.9875092495},
{"learn":[4.390505974],"iteration":321,"passed_time":0.4675110363,"remaining_time":0.984386592},
{"learn":[4.390305136],"iteration":322,"passed_time":0.468134327,"remaining_time":0.9811979546},
{"learn":[4.38568203],"iteration":323,"passed_time":0.4687429414,"remaining_time":0.9779945321},
{"learn":[4.383057135],"iteration":324,"passed_time":0.469358689,"remaining_time":0.9748218926},
{"learn":[4.380662684],"iteration":325,"passed_time":0.4699328334,"remaining_time":0.9715789254},
{"learn":[4.37805727],"iteration":326,"passed_time":0.4705184386,"remaining_time":0.9683758691},
{"learn":[4.373708319],"iteration":327,"passed_time":0.4710755567,"remaining_time":0.9651304089},
{"learn":[4.36887921],"iteration":328,"passed_time":0.4716929387,"remaining_time":0.9620242003},
{"learn":[4.367895929],"iteration":329,"passed_time":0.472263992,"remaining_time":0.9588390141},
{"learn":[4.362140573],"iteration":330,"passed_time":0.472926279,"remaining_time":0.9558540202},
{"learn":[4.361931924],"iteration":331,"passed_time":0.4735192871,"remaining_time":0.9527436259},
{"learn":[4.359656377],"iteration":332,"passed_time":0.4741114922,"remaining_time":0.9496467426},
{"learn":[4.354281355],"iteration":333,"passed_time":0.4746829968,"remaining_time":0.9465235804},
{"learn":[4.348589447],"iteration":334,"passed_time":0.475327066,"remaining_time":0.9435596983},
{"learn":[4.346355698],"iteration":335,"passed_time":0.4758819811,"remaining_time":0.9404334389},
{"learn":[4.343894047],"iteration":336,"passed_time":0.4764806527,"remaining_time":0.9374085244},
{"learn":[4.341561356],"iteration":337,"passed_time":0.4770827003,"remaining_time":0.9344045787},
{"learn":[4.338869061],"iteration":338,"passed_time":0.4776960242,"remaining_time":0.9314367906},
{"learn":[4.333720063],"iteration":339,"passed_time":0.478374054,"remaining_time":0.9286084578},
{"learn":[4.330892223],"iteration":340,"passed_time":0.4789704712,"remaining_time":0.9256350162},
{"learn":[4.328311474],"iteration":341,"passed_time":0.4795386342,"remaining_time":0.9226211148},
{"learn":[4.324580133],"iteration":342,"passed_time":0.4801053542,"remaining_time":0.9196187106},
{"learn":[4.323354432],"iteration":343,"passed_time":0.4807163188,"remaining_time":0.9167148405},
{"learn":[4.323159553],"iteration":344,"passed_time":0.4812500637,"remaining_time":0.9136776572},
{"learn":[4.318639682],"iteration":345,"passed_time":0.4818346254,"remaining_time":0.9107509971},
{"learn":[4.312712208],"iteration":346,"passed_time":0.4824312157,"remaining_time":0.9078604722},
{"learn":[4.311461062],"iteration":347,"passed_time":0.4830416937,"remaining_time":0.9050091503},
{"learn":[4.311178356],"iteration":348,"passed_time":0.4836355486,"remaining_time":0.9021396622},
{"learn":[4.311102505],"iteration":349,"passed_time":0.4841883963,"remaining_time":0.8992070217},
{"learn":[4.310232308],"iteration":350,"passed_time":0.484719034,"remaining_time":0.8962468749},
{"learn":[4.305128197],"iteration":351,"passed_time":0.4853002586,"remaining_time":0.8933936579},
{"learn":[4.304595496],"iteration":352,"passed_time":0.4858726927,"remaining_time":0.8905372015},
{"learn":[4.3004992],"iteration":353,"passed_time":0.48645837,"remaining_time":0.8877178164},
{"learn":[4.297581524],"iteration":354,"passed_time":0.4870647247,"remaining_time":0.8849485844},
{"learn":[4.297355825],"iteration":355,"passed_time":0.4876132423,"remaining_time":0.8820868766},
{"learn":[4.295758715],"iteration":356,"passed_time":0.4881777885,"remaining_time":0.8792669973},
{"learn":[4.292500657],"iteration":357,"passed_time":0.4887669209,"remaining_time":0.8765038079},
{"learn":[4.290797586],"iteration":358,"passed_time":0.4893134999,"remaining_time":0.8736767505},
{"learn":[4.286410608],"iteration":359,"passed_time":0.4898858044,"remaining_time":0.8709080968},
{"learn":[4.280278245],"iteration":360,"passed_time":0.490451579,"remaining_time":0.8681400525},
{"learn":[4.279941283],"iteration":361,"passed_time":0.4909944255,"remaining_time":0.8653437665},
{"learn":[4.274426275],"iteration":362,"passed_time":0.4916091716,"remaining_time":0.8626860669},
{"learn":[4.273567658],"iteration":363,"passed_time":0.4921978196,"remaining_time":0.8599939926},
{"learn":[4.269488271],"iteration":364,"passed_time":0.4928433099,"remaining_time":0.8574123337},
{"learn":[4.266838205],"iteration":365,"passed_time":0.4934825954,"remaining_time":0.8548305068},
{"learn":[4.263456509],"iteration":366,"passed_time":0.4941098997,"remaining_time":0.8522386009},
{"learn":[4.260360204],"iteration":367,"passed_time":0.4947371335,"remaining_time":0.849657251},
{"learn":[4.255120549],"iteration":368,"passed_time":0.4953777937,"remaining_time":0.8471094521},
{"learn":[4.252582211],"iteration":369,"passed_time":0.4960025371,"remaining_time":0.8445448605},
{"learn":[4.247857931],"iteration":370,"passed_time":0.4966046384,"remaining_time":0.8419523385},
{"learn":[4.245288911],"iteration":371,"passed_time":0.4971443157,"remaining_time":0.8392651351},
{"learn":[4.24048515],"iteration":372,"passed_time":0.4977406861,"remaining_time":0.8366847459},
{"learn":[4.2378365],"iteration":373,"passed_time":0.4983471022,"remaining_time":0.8341317807},
{"learn":[4.236751063],"iteration":374,"passed_time":0.4989572554,"remaining_time":0.8315954256},
{"learn":[4.233240093],"iteration":375,"passed_time":0.4995534112,"remaining_time":0.8290460867},
{"learn":[4.230358421],"iteration":376,"passed_time":0.500154321,"remaining_time":0.8265149655},
{"learn":[4.225853583],"iteration":377,"passed_time":0.5007204955,"remaining_time":0.8239369},
{"learn":[4.224702126],"iteration":378,"passed_time":0.5013085375,"remaining_time":0.8214052817},
{"learn":[4.224361982],"iteration":379,"passed_time":0.5018958285,"remaining_time":0.8188826676},
{"learn":[4.223787954],"iteration":380,"passed_time":0.5024627815,"remaining_time":0.81633717},
{"learn":[4.22144054],"iteration":381,"passed_time":0.5030150048,"remaining_time":0.8137782014},
{"learn":[4.217739335],"iteration":382,"passed_time":0.5036038574,"remaining_time":0.8112887207},
{"learn":[4.215611665],"iteration":383,"passed_time":0.5042066606,"remaining_time":0.8088315181},
{"learn":[4.210236863],"iteration":384,"passed_time":0.504809617,"remaining_time":0.8063841935},
{"learn":[4.208454294],"iteration":385,"passed_time":0.5054169113,"remaining_time":0.8039533252},
{"learn":[4.207446501],"iteration":386,"passed_time":0.5059670166,"remaining_time":0.801441295},
{"learn":[4.204985442],"iteration":387,"passed_time":0.5065416322,"remaining_time":0.7989780383},
{"learn":[4.202796622],"iteration":388,"passed_time":0.5071755006,"remaining_time":0.7966175601},
{"learn":[4.199774004],"iteration":389,"passed_time":0.5077924397,"remaining_time":0.794239457},
{"learn":[4.199458358],"iteration":390,"passed_time":0.5083397459,"remaining_time":0.791761906},
{"learn":[4.19751254],"iteration":391,"passed_time":0.5089483419,"remaining_time":0.7893892651},
{"learn":[4.195201346],"iteration":392,"passed_time":0.509516534,"remaining_time":0.7869631963},
{"learn":[4.190593508],"iteration":393,"passed_time":0.510108877,"remaining_time":0.7845837042},
{"learn":[4.187212054],"iteration":394,"passed_time":0.510693765,"remaining_time":0.7822018427},
{"learn":[4.184984466],"iteration":395,"passed_time":0.5112567872,"remaining_time":0.7797957057},
{"learn":[4.182832144],"iteration":396,"passed_time":0.5118001494,"remaining_time":0.7773689926},
{"learn":[4.179752812],"iteration":397,"passed_time":0.5123430028,"remaining_time":0.7749509741},
{"learn":[4.17878934],"iteration":398,"passed_time":0.5129194068,"remaining_time":0.772592891},
{"learn":[4.174548229],"iteration":399,"passed_time":0.5135384585,"remaining_time":0.7703076878},
{"learn":[4.168872556],"iteration":400,"passed_time":0.5142015038,"remaining_time":0.7680965107},
{"learn":[4.163926494],"iteration":401,"passed_time":0.5148073053,"remaining_time":0.7658078821},
{"learn":[4.159485076],"iteration":402,"passed_time":0.5154726812,"remaining_time":0.7636158577},
{"learn":[4.155926102],"iteration":403,"passed_time":0.5161088074,"remaining_time":0.7613882406},
{"learn":[4.153540115],"iteration":404,"passed_time":0.5167266967,"remaining_time":0.7591416902},
{"learn":[4.150983044],"iteration":405,"passed_time":0.5173290363,"remaining_time":0.7568804127},
{"learn":[4.146539132],"iteration":406,"passed_time":0.5179156967,"remaining_time":0.7546044426},
{"learn":[4.144869174],"iteration":407,"passed_time":0.5184930869,"remaining_time":0.7523233025},
{"learn":[4.142825962],"iteration":408,"passed_time":0.5190597196,"remaining_time":0.7500349494},
{"learn":[4.142467378],"iteration":409,"passed_time":0.5196051561,"remaining_time":0.7477244929},
{"learn":[4.141800768],"iteration":410,"passed_time":0.5201605578,"remaining_time":0.7454369064},
{"learn":[4.140107084],"iteration":411,"passed_time":0.5207020112,"remaining_time":0.7431378219},
{"learn":[4.136243196],"iteration":412,"passed_time":0.5213111812,"remaining_time":0.7409434949},
{"learn":[4.133618439],"iteration":413,"passed_time":0.5219657321,"remaining_time":0.7388210605},
{"learn":[4.131053025],"iteration":414,"passed_time":0.5225591356,"remaining_time":0.7366195045},
{"learn":[4.128379975],"iteration":415,"passed_time":0.5231298142,"remaining_time":0.7343937776},
{"learn":[4.127068571],"iteration":416,"passed_time":0.5237012537,"remaining_time":0.7321770525},
{"learn":[4.125969877],"iteration":417,"passed_time":0.5242299259,"remaining_time":0.7299086529},
{"learn":[4.123893633],"iteration":418,"passed_time":0.5248146807,"remaining_time":0.7277263233},
{"learn":[4.119643722],"iteration":419,"passed_time":0.5254163099,"remaining_time":0.7255749042},
{"learn":[4.11465686],"iteration":420,"passed_time":0.5260120827,"remaining_time":0.7234227931},
{"learn":[4.111565986],"iteration":421,"passed_time":0.5266170345,"remaining_time":0.7212906301},
{"learn":[4.106322452],"iteration":422,"passed_time":0.5272545078,"remaining_time":0.7192100496},
{"learn":[4.104222175],"iteration":423,"passed_time":0.5279456199,"remaining_time":0.717209144},
{"learn":[4.103008002],"iteration":424,"passed_time":0.5285316666,"remaining_time":0.7150722548},
{"learn":[4.099176337],"iteration":425,"passed_time":0.5291613179,"remaining_time":0.7130014002},
{"learn":[4.096525716],"iteration":426,"passed_time":0.5297295636,"remaining_time":0.7108548945},
{"learn":[4.094967724],"iteration":427,"passed_time":0.5303146539,"remaining_time":0.7087382758},
{"learn":[4.094683584],"iteration":428,"passed_time":0.5308818889,"remaining_time":0.7066050317},
{"learn":[4.091096563],"iteration":429,"passed_time":0.5314819665,"remaining_time":0.7045226068},
{"learn":[4.089178677],"iteration":430,"passed_time":0.5320728575,"remaining_time":0.7024349325},
{"learn":[4.085335077],"iteration":431,"passed_time":0.5326120666,"remaining_time":0.7002862357},
{"learn":[4.084852122],"iteration":432,"passed_time":0.533199707,"remaining_time":0.6982083923},
{"learn":[4.080322952],"iteration":433,"passed_time":0.5337950836,"remaining_time":0.6961475054},
{"learn":[4.077449519],"iteration":434,"passed_time":0.5343773557,"remaining_time":0.6940763355},
{"learn":[4.076568374],"iteration":435,"passed_time":0.534922206,"remaining_time":0.6919635875},
{"learn":[4.076071793],"iteration":436,"passed_time":0.5355509447,"remaining_time":0.6899660912},
{"learn":[4.075027644],"iteration":437,"passed_time":0.5361142066,"remaining_time":0.6878908313},
{"learn":[4.07020837],"iteration":438,"passed_time":0.5367577759,"remaining_time":0.6859250849},
{"learn":[4.06833694],"iteration":439,"passed_time":0.5373750131,"remaining_time":0.6839318348},
{"learn":[4.063936568],"iteration":440,"passed_time":0.5379534899,"remaining_time":0.6818956935},
{"learn":[4.061734926],"iteration":441,"passed_time":0.5385278166,"remaining_time":0.6798609087},
{"learn":[4.060815619],"iteration":442,"passed_time":0.5391042927,"remaining_time":0.6778354199},
{"learn":[4.056407489],"iteration":443,"passed_time":0.5396696158,"remaining_time":0.6758024919},
{"learn":[4.05238936],"iteration":444,"passed_time":0.5403057398,"remaining_time":0.673864462},
{"learn":[4.049685254],"iteration":445,"passed_time":0.5408792029,"remaining_time":0.6718544359},
{"learn":[4.045162016],"iteration":446,"passed_time":0.5414767986,"remaining_time":0.6698806927},
{"learn":[4.042955482],"iteration":447,"passed_time":0.5420657877,"remaining_time":0.6679024884},
{"learn":[4.041467663],"iteration":448,"passed_time":0.5426576977,"remaining_time":0.6659340567},
{"learn":[4.038920476],"iteration":449,"passed_time":0.5432381645,"remaining_time":0.6639577566},
{"learn":[4.036694383],"iteration":450,"passed_time":0.5438283665,"remaining_time":0.6619994972},
{"learn":[4.034999007],"iteration":451,"passed_time":0.5444156867,"remaining_time":0.6600437971},
{"learn":[4.031928018],"iteration":452,"passed_time":0.5449908371,"remaining_time":0.6580794435},
{"learn":[4.028718143],"iteration":453,"passed_time":0.5455678733,"remaining_time":0.6561234776},
{"learn":[4.027401978],"iteration":454,"passed_time":0.5461959492,"remaining_time":0.6542347084},
{"learn":[4.025930598],"iteration":455,"passed_time":0.5467874639,"remaining_time":0.6523078517},
{"learn":[4.021074523],"iteration":456,"passed_time":0.5473672793,"remaining_time":0.650372938},
{"learn":[4.020268486],"iteration":457,"passed_time":0.5479341787,"remaining_time":0.6484286569},
{"learn":[4.017986361],"iteration":458,"passed_time":0.5484923918,"remaining_time":0.6464801393},
{"learn":[4.014814804],"iteration":459,"passed_time":0.5491014369,"remaining_time":0.644597339},
{"learn":[4.009704796],"iteration":460,"passed_time":0.5496966457,"remaining_time":0.6427038873},
{"learn":[4.008440457],"iteration":461,"passed_time":0.5503510518,"remaining_time":0.640884991},
{"learn":[4.004854849],"iteration":462,"passed_time":0.5516089863,"remaining_time":0.6397711137},
{"learn":[4.000898028],"iteration":463,"passed_time":0.5523320621,"remaining_time":0.6380387614},
{"learn":[3.996617985],"iteration":464,"passed_time":0.5530375918,"remaining_time":0.6362905627},
{"learn":[3.995443319],"iteration":465,"passed_time":0.5537505565,"remaining_time":0.6345553588},
{"learn":[3.990771995],"iteration":466,"passed_time":0.5545402969,"remaining_time":0.6329121589},
{"learn":[3.989249359],"iteration":467,"passed_time":0.5551507105,"remaining_time":0.6310687564},
{"learn":[3.986599538],"iteration":468,"passed_time":0.5557741789,"remaining_time":0.6292453923},
{"learn":[3.985628919],"iteration":469,"passed_time":0.5563536725,"remaining_time":0.6273775456},
{"learn":[3.985086112],"iteration":470,"passed_time":0.5568945114,"remaining_time":0.6254717549},
{"learn":[3.98466839],"iteration":471,"passed_time":0.5575797556,"remaining_time":0.6237332859},
{"learn":[3.984233894],"iteration":472,"passed_time":0.5581501368,"remaining_time":0.6218712941},
{"learn":[3.981855845],"iteration":473,"passed_time":0.5587423051,"remaining_time":0.6200389293},
{"learn":[3.978684264],"iteration":474,"passed_time":0.559332629,"remaining_time":0.6182097479},
{"learn":[3.974361269],"iteration":475,"passed_time":0.5600397682,"remaining_time":0.6165143667},
{"learn":[3.972074049],"iteration":476,"passed_time":0.5606847455,"remaining_time":0.6147549725},
{"learn":[3.97191982],"iteration":477,"passed_time":0.5612599289,"remaining_time":0.6129240228},
{"learn":[3.969616848],"iteration":478,"passed_time":0.5618591881,"remaining_time":0.6111245032},
{"learn":[3.968533527],"iteration":479,"passed_time":0.5624226991,"remaining_time":0.6092912574},
{"learn":[3.967568753],"iteration":480,"passed_time":0.5630149777,"remaining_time":0.6074943315},
{"learn":[3.966232553],"iteration":481,"passed_time":0.5636680957,"remaining_time":0.6057677875},
{"learn":[3.961522393],"iteration":482,"passed_time":0.5642311623,"remaining_time":0.6039492979},
{"learn":[3.955829553],"iteration":483,"passed_time":0.5648144358,"remaining_time":0.602157539},
{"learn":[3.954248095],"iteration":484,"passed_time":0.5653757017,"remaining_time":0.6003473946},
{"learn":[3.951922606],"iteration":485,"passed_time":0.565951885,"remaining_time":0.5985581665},
{"learn":[3.94978202],"iteration":486,"passed_time":0.5665261811,"remaining_time":0.5967719321},
{"learn":[3.949518999],"iteration":487,"passed_time":0.5670723409,"remaining_time":0.5949611446},
{"learn":[3.945431216],"iteration":488,"passed_time":0.5676645897,"remaining_time":0.5932036919},
{"learn":[3.943249086],"iteration":489,"passed_time":0.5682689859,"remaining_time":0.5914636384},
{"learn":[3.941981548],"iteration":490,"passed_time":0.5688302717,"remaining_time":0.5896835199},
{"learn":[3.936600517],"iteration":491,"passed_time":0.5693999043,"remaining_time":0.5879169743},
{"learn":[3.934476885],"iteration":492,"passed_time":0.5699707706,"remaining_time":0.5861565531},
{"learn":[3.93045798],"iteration":493,"passed_time":0.5705535124,"remaining_time":0.5844131118},
{"learn":[3.925977375],"iteration":494,"passed_time":0.5711538421,"remaining_time":0.5826923035},
{"learn":[3.92457993],"iteration":495,"passed_time":0.5717463597,"remaining_time":0.5809680752},
{"learn":[3.919849146],"iteration":496,"passed_time":0.572340213,"remaining_time":0.5792497528},
{"learn":[3.919681964],"iteration":497,"passed_time":0.5729066879,"remaining_time":0.577508348},
{"learn":[3.917633027],"iteration":498,"passed_time":0.5735054429,"remaining_time":0.5758040619},
{"learn":[3.916616419],"iteration":499,"passed_time":0.5742363224,"remaining_time":0.5742363224},
{"learn":[3.912896166],"iteration":500,"passed_time":0.5749251947,"remaining_time":0.5726300842},
{"learn":[3.912769674],"iteration":501,"passed_time":0.5756022284,"remaining_time":0.5710157565},
{"learn":[3.909373788],"iteration":502,"passed_time":0.5762900472,"remaining_time":0.569415812},
{"learn":[3.906706036],"iteration":503,"passed_time":0.5768939239,"remaining_time":0.5677368775},
{"learn":[3.903895664],"iteration":504,"passed_time":0.5775434351,"remaining_time":0.5661069315},
{"learn":[3.902982967],"iteration":505,"passed_time":0.5781548963,"remaining_time":0.5644437129},
{"learn":[3.900905528],"iteration":506,"passed_time":0.57874387,"remaining_time":0.5627627769},
{"learn":[3.897463465],"iteration":507,"passed_time":0.5793410305,"remaining_time":0.5610940689},
{"learn":[3.895918033],"iteration":508,"passed_time":0.5799273162,"remaining_time":0.559419081},
{"learn":[3.893921936],"iteration":509,"passed_time":0.5804849423,"remaining_time":0.5577208269},
{"learn":[3.890237934],"iteration":510,"passed_time":0.5810513804,"remaining_time":0.5560354697},
{"learn":[3.887311613],"iteration":511,"passed_time":0.5816165396,"remaining_time":0.5543532643},
{"learn":[3.884869735],"iteration":512,"passed_time":0.5822356664,"remaining_time":0.5527266462},
{"learn":[3.882101231],"iteration":513,"passed_time":0.5828276753,"remaining_time":0.5510783077},
{"learn":[3.88060368],"iteration":514,"passed_time":0.5834309573,"remaining_time":0.549444688},
{"learn":[3.877726076],"iteration":515,"passed_time":0.5840322418,"remaining_time":0.547813188},
{"learn":[3.874938145],"iteration":516,"passed_time":0.584616408,"remaining_time":0.546169681},
{"learn":[3.874340833],"iteration":517,"passed_time":0.5851845411,"remaining_time":0.5445153452},
{"learn":[3.873105224],"iteration":518,"passed_time":0.5857567254,"remaining_time":0.5428689497},
{"learn":[3.869800236],"iteration":519,"passed_time":0.5863611407,"remaining_time":0.5412564376},
{"learn":[3.867932518],"iteration":520,"passed_time":0.5869341748,"remaining_time":0.5396189438},
{"learn":[3.866666962],"iteration":521,"passed_time":0.5875052411,"remaining_time":0.5379837265},
{"learn":[3.865527652],"iteration":522,"passed_time":0.5881865911,"remaining_time":0.5364531624},
{"learn":[3.861900081],"iteration":523,"passed_time":0.5888128027,"remaining_time":0.5348757521},
{"learn":[3.858502887],"iteration":524,"passed_time":0.5893657707,"remaining_time":0.5332356973},
{"learn":[3.858335097],"iteration":525,"passed_time":0.589915722,"remaining_time":0.5315970575},
{"learn":[3.855719306],"iteration":526,"passed_time":0.5905581492,"remaining_time":0.5300455494},
{"learn":[3.855137428],"iteration":527,"passed_time":0.5911242907,"remaining_time":0.5284292902},
{"learn":[3.851985706],"iteration":528,"passed_time":0.5917046885,"remaining_time":0.5268296943},
{"learn":[3.851051809],"iteration":529,"passed_time":0.5922782283,"remaining_time":0.5252278628},
{"learn":[3.850679146],"iteration":530,"passed_time":0.5928255973,"remaining_time":0.5236067893},
{"learn":[3.848179484],"iteration":531,"passed_time":0.5934176705,"remaining_time":0.5220290786},
{"learn":[3.844551071],"iteration":532,"passed_time":0.5940225196,"remaining_time":0.5204662601},
{"learn":[3.841604794],"iteration":533,"passed_time":0.5946050859,"remaining_time":0.5188875843},
{"learn":[3.83969656],"iteration":534,"passed_time":0.5951917371,"remaining_time":0.5173161827},
{"learn":[3.836811463],"iteration":535,"passed_time":0.5957592901,"remaining_time":0.5157319228},
{"learn":[3.834182551],"iteration":536,"passed_time":0.5963411154,"remaining_time":0.514163755},
{"learn":[3.828012842],"iteration":537,"passed_time":0.5969046801,"remaining_time":0.5125835728},
{"learn":[3.826636176],"iteration":538,"passed_time":0.5974864824,"remaining_time":0.5110227614},
{"learn":[3.826189798],"iteration":539,"passed_time":0.5980593977,"remaining_time":0.5094580054},
{"learn":[3.824104738],"iteration":540,"passed_time":0.598631916,"remaining_time":0.5078965794},
{"learn":[3.82300218],"iteration":541,"passed_time":0.5992106686,"remaining_time":0.5063440705},
{"learn":[3.817146402],"iteration":542,"passed_time":0.5998348573,"remaining_time":0.5048333882},
{"learn":[3.814638044],"iteration":543,"passed_time":0.6004336262,"remaining_time":0.5033046572},
{"learn":[3.812979573],"iteration":544,"passed_time":0.6010641119,"remaining_time":0.5018058182},
{"learn":[3.811938825],"iteration":545,"passed_time":0.6017580328,"remaining_time":0.5003629064},
{"learn":[3.811479418],"iteration":546,"passed_time":0.6023671025,"remaining_time":0.4988524633},
{"learn":[3.80742981],"iteration":547,"passed_time":0.6029707868,"remaining_time":0.497340868},
{"learn":[3.805097043],"iteration":548,"passed_time":0.6036069337,"remaining_time":0.4958592479},
{"learn":[3.801577232],"iteration":549,"passed_time":0.6042015701,"remaining_time":0.4943467392},
{"learn":[3.799762083],"iteration":550,"passed_time":0.6047648405,"remaining_time":0.4928120025},
{"learn":[3.796393455],"iteration":551,"passed_time":0.605341715,"remaining_time":0.4912918267},
{"learn":[3.793486459],"iteration":552,"passed_time":0.6059271372,"remaining_time":0.4897819716},
{"learn":[3.792006091],"iteration":553,"passed_time":0.6064846568,"remaining_time":0.4882529908},
{"learn":[3.78932128],"iteration":554,"passed_time":0.6070970949,"remaining_time":0.4867715446},
{"learn":[3.787581812],"iteration":555,"passed_time":0.6076870403,"remaining_time":0.4852752624},
{"learn":[3.785308865],"iteration":556,"passed_time":0.6082589203,"remaining_time":0.4837678666},
{"learn":[3.78465475],"iteration":557,"passed_time":0.6088382032,"remaining_time":0.4822696878},
{"learn":[3.780498869],"iteration":558,"passed_time":0.6094192929,"remaining_time":0.4807762221},
{"learn":[3.778734909],"iteration":559,"passed_time":0.6099947215,"remaining_time":0.4792815669},
{"learn":[3.778652349],"iteration":560,"passed_time":0.6105697394,"remaining_time":0.4777898674},
{"learn":[3.777928006],"iteration":561,"passed_time":0.6111520689,"remaining_time":0.4763071284},
{"learn":[3.776131406],"iteration":562,"passed_time":0.6117196472,"remaining_time":0.4748161382},
{"learn":[3.772925617],"iteration":563,"passed_time":0.6123265322,"remaining_time":0.4733588086},
{"learn":[3.7727745],"iteration":564,"passed_time":0.6128856234,"remaining_time":0.4718676924},
{"learn":[3.771763073],"iteration":565,"passed_time":0.6134607509,"remaining_time":0.4703921659},
{"learn":[3.768738162],"iteration":566,"passed_time":0.6140367749,"remaining_time":0.4689205},
{"learn":[3.767220794],"iteration":567,"passed_time":0.6146101645,"remaining_time":0.4674499842},
{"learn":[3.766691102],"iteration":568,"passed_time":0.6151948525,"remaining_time":0.46599118},
{"learn":[3.766259335],"iteration":569,"passed_time":0.615806506,"remaining_time":0.4645557852},
{"learn":[3.76116362],"iteration":570,"passed_time":0.616358471,"remaining_time":0.4630784309},
{"learn":[3.758633056],"iteration":571,"passed_time":0.6169142558,"remaining_time":0.4616071704},
{"learn":[3.754603809],"iteration":572,"passed_time":0.6175458691,"remaining_time":0.4601956128},
{"learn":[3.754070549],"iteration":573,"passed_time":0.6182089768,"remaining_time":0.4588101466},
{"learn":[3.750534319],"iteration":574,"passed_time":0.6188525848,"remaining_time":0.4574127801},
{"learn":[3.746491516],"iteration":575,"passed_time":0.619557862,"remaining_time":0.4560634262},
{"learn":[3.744210544],"iteration":576,"passed_time":0.6202070422,"remaining_time":0.45467518},
{"learn":[3.742929991],"iteration":577,"passed_time":0.6208517934,"remaining_time":0.4532862575},
{"learn":[3.740402992],"iteration":578,"passed_time":0.6214945194,"remaining_time":0.451898433},
{"learn":[3.739644243],"iteration":579,"passed_time":0.6221860936,"remaining_time":0.4505485506},
{"learn":[3.737529404],"iteration":580,"passed_time":0.6228436736,"remaining_time":0.4491764186},
{"learn":[3.737196923],"iteration":581,"passed_time":0.6234188853,"remaining_time":0.4477475843},
{"learn":[3.733954464],"iteration":582,"passed_time":0.6239939714,"remaining_time":0.4463215885},
{"learn":[3.731608623],"iteration":583,"passed_time":0.6246026771,"remaining_time":0.4449224549},
{"learn":[3.729843952],"iteration":584,"passed_time":0.6252039339,"remaining_time":0.4435207395},
{"learn":[3.727223798],"iteration":585,"passed_time":0.6257814598,"remaining_time":0.4421049904},
{"learn":[3.725351667],"iteration":586,"passed_time":0.626496739,"remaining_time":0.4407890174},
{"learn":[3.725026912],"iteration":587,"passed_time":0.6270821006,"remaining_time":0.4393840569},
{"learn":[3.721974565],"iteration":588,"passed_time":0.6277114577,"remaining_time":0.4380125791},
{"learn":[3.720269493],"iteration":589,"passed_time":0.6282928447,"remaining_time":0.4366102819},
{"learn":[3.718907466],"iteration":590,"passed_time":0.6288775212,"remaining_time":0.4352130392},
{"learn":[3.715602912],"iteration":591,"passed_time":0.629445665,"remaining_time":0.4338071475},
{"learn":[3.714463059],"iteration":592,"passed_time":0.6300082772,"remaining_time":0.4324002847},
{"learn":[3.710802077],"iteration":593,"passed_time":0.6305688335,"remaining_time":0.4309948592},
{"learn":[3.708032435],"iteration":594,"passed_time":0.6311563498,"remaining_time":0.4296106247},
{"learn":[3.703788939],"iteration":595,"passed_time":0.6317872739,"remaining_time":0.4282584877},
{"learn":[3.702500944],"iteration":596,"passed_time":0.6323865676,"remaining_time":0.426887415},
{"learn":[3.698196925],"iteration":597,"passed_time":0.6329768792,"remaining_time":0.4255128854},
{"learn":[3.69658891],"iteration":598,"passed_time":0.6335574793,"remaining_time":0.4241344728},
{"learn":[3.696124066],"iteration":599,"passed_time":0.6341295019,"remaining_time":0.4227530013},
{"learn":[3.693537052],"iteration":600,"passed_time":0.6347510202,"remaining_time":0.4214070833},
{"learn":[3.691343275],"iteration":601,"passed_time":0.6353536379,"remaining_time":0.4200510762},
{"learn":[3.690973831],"iteration":602,"passed_time":0.6359242245,"remaining_time":0.4186764795},
{"learn":[3.686151073],"iteration":603,"passed_time":0.6365010286,"remaining_time":0.4173086214},
{"learn":[3.683921982],"iteration":604,"passed_time":0.6371297259,"remaining_time":0.4159772591},
{"learn":[3.679975271],"iteration":605,"passed_time":0.6377166959,"remaining_time":0.4146210861},
{"learn":[3.674047638],"iteration":606,"passed_time":0.6382769503,"remaining_time":0.4132501507},
{"learn":[3.673151794],"iteration":607,"passed_time":0.638872264,"remaining_time":0.411904486},
{"learn":[3.670953108],"iteration":608,"passed_time":0.6394645848,"remaining_time":0.410559364},
{"learn":[3.6703947],"iteration":609,"passed_time":0.6400515586,"remaining_time":0.4092132916},
{"learn":[3.668433805],"iteration":610,"passed_time":0.640633151,"remaining_time":0.4078662778},
{"learn":[3.668304956],"iteration":611,"passed_time":0.6412602078,"remaining_time":0.4065505892},
{"learn":[3.667880012],"iteration":612,"passed_time":0.6418387734,"remaining_time":0.405206534},
{"learn":[3.667282264],"iteration":613,"passed_time":0.6424138342,"remaining_time":0.4038627688},
{"learn":[3.664611483],"iteration":614,"passed_time":0.6430188121,"remaining_time":0.4025402319},
{"learn":[3.662543394],"iteration":615,"passed_time":0.6435846425,"remaining_time":0.4011956213},
{"learn":[3.659041959],"iteration":616,"passed_time":0.6441810566,"remaining_time":0.3998725197},
{"learn":[3.656868545],"iteration":617,"passed_time":0.6447770003,"remaining_time":0.3985514791},
{"learn":[3.654785614],"iteration":618,"passed_time":0.6453184146,"remaining_time":0.3971992181},
{"learn":[3.654566096],"iteration":619,"passed_time":0.6458565019,"remaining_time":0.3958475334},
{"learn":[3.651007045],"iteration":620,"passed_time":0.6464977391,"remaining_time":0.3945614221},
{"learn":[3.648921786],"iteration":621,"passed_time":0.6471071068,"remaining_time":0.3932580167},
{"learn":[3.647655706],"iteration":622,"passed_time":0.6476540896,"remaining_time":0.3919190879},
{"learn":[3.647241144],"iteration":623,"passed_time":0.6482397638,"remaining_time":0.3906060115},
{"learn":[3.644195689],"iteration":624,"passed_time":0.6487991654,"remaining_time":0.3892794992},
{"learn":[3.642632246],"iteration":625,"passed_time":0.6493649974,"remaining_time":0.3879592796},
{"learn":[3.642523322],"iteration":626,"passed_time":0.6498217379,"remaining_time":0.3865765682},
{"learn":[3.641494659],"iteration":627,"passed_time":0.6503752239,"remaining_time":0.3852541135},
{"learn":[3.63976496],"iteration":628,"passed_time":0.6509229124,"remaining_time":0.3839306844},
{"learn":[3.637945652],"iteration":629,"passed_time":0.6515122839,"remaining_time":0.3826341985},
{"learn":[3.636233667],"iteration":630,"passed_time":0.652066353,"remaining_time":0.3813193095},
{"learn":[3.635304404],"iteration":631,"passed_time":0.6526124232,"remaining_time":0.3800021705},
{"learn":[3.632234951],"iteration":632,"passed_time":0.6532070366,"remaining_time":0.3787156121},
{"learn":[3.631630987],"iteration":633,"passed_time":0.653805125,"remaining_time":0.3774332425},
{"learn":[3.630301009],"iteration":634,"passed_time":0.6543764511,"remaining_time":0.3761376451},
{"learn":[3.629077964],"iteration":635,"passed_time":0.6549506345,"remaining_time":0.3748459606},
{"learn":[3.628004522],"iteration":636,"passed_time":0.6555049688,"remaining_time":0.3735452177},
{"learn":[3.625062876],"iteration":637,"passed_time":0.6560675219,"remaining_time":0.372251478},
{"learn":[3.624917986],"iteration":638,"passed_time":0.6565876251,"remaining_time":0.3709360449},
{"learn":[3.622887087],"iteration":639,"passed_time":0.6571999115,"remaining_time":0.3696749502},
{"learn":[3.621220865],"iteration":640,"passed_time":0.6578035798,"remaining_time":0.3684110533},
{"learn":[3.621143844],"iteration":641,"passed_time":0.6583573402,"remaining_time":0.3671213828},
{"learn":[3.620822821],"iteration":642,"passed_time":0.6588867404,"remaining_time":0.3658204764},
{"learn":[3.619202826],"iteration":643,"passed_time":0.6594436355,"remaining_time":0.364537165},
{"learn":[3.618204882],"iteration":644,"passed_time":0.6600252677,"remaining_time":0.363269721},
{"learn":[3.614259666],"iteration":645,"passed_time":0.6606744134,"remaining_time":0.3620413968},
{"learn":[3.613415661],"iteration":646,"passed_time":0.6613003239,"remaining_time":0.360802186},
{"learn":[3.611096773],"iteration":647,"passed_time":0.6619265424,"remaining_time":0.3595650354},
{"learn":[3.610820695],"iteration":648,"passed_time":0.6625260415,"remaining_time":0.3583153167},
{"learn":[3.609290065],"iteration":649,"passed_time":0.6631104353,"remaining_time":0.3570594652},
{"learn":[3.60897947],"iteration":650,"passed_time":0.6636855007,"remaining_time":0.3558006755},
{"learn":[3.606570702],"iteration":651,"passed_time":0.6642536452,"remaining_time":0.3545402892},
{"learn":[3.606292637],"iteration":652,"passed_time":0.6648015851,"remaining_time":0.3532712864},
{"learn":[3.602753838],"iteration":653,"passed_time":0.6653733563,"remaining_time":0.3520170968},
{"learn":[3.599755869],"iteration":654,"passed_time":0.6659534108,"remaining_time":0.3507693538},
{"learn":[3.599509575],"iteration":655,"passed_time":0.6665526647,"remaining_time":0.3495337144},
{"learn":[3.595337722],"iteration":656,"passed_time":0.6671231946,"remaining_time":0.3482850164},
{"learn":[3.595168561],"iteration":657,"passed_time":0.6677040659,"remaining_time":0.3470437546},
{"learn":[3.59290559],"iteration":658,"passed_time":0.6683239505,"remaining_time":0.3458246846},
{"learn":[3.592015928],"iteration":659,"passed_time":0.6688841773,"remaining_time":0.3445766974},
{"learn":[3.590680403],"iteration":660,"passed_time":0.6694665551,"remaining_time":0.3433421516},
{"learn":[3.590361532],"iteration":661,"passed_time":0.6700853486,"remaining_time":0.3421281689},
{"learn":[3.589069739],"iteration":662,"passed_time":0.6706490841,"remaining_time":0.340887996},
{"learn":[3.585010186],"iteration":663,"passed_time":0.6712391091,"remaining_time":0.3396631637},
{"learn":[3.582997552],"iteration":664,"passed_time":0.6718604113,"remaining_time":0.3384559967},
{"learn":[3.582119256],"iteration":665,"passed_time":0.6724351603,"remaining_time":0.3372272425},
{"learn":[3.579019356],"iteration":666,"passed_time":0.6729919519,"remaining_time":0.3359914842},
{"learn":[3.57719559],"iteration":667,"passed_time":0.6735989281,"remaining_time":0.3347827008},
{"learn":[3.574050046],"iteration":668,"passed_time":0.6741780126,"remaining_time":0.3335619165},
{"learn":[3.572204518],"iteration":669,"passed_time":0.6747537461,"remaining_time":0.3323413973},
{"learn":[3.569508025],"iteration":670,"passed_time":0.6757504413,"remaining_time":0.331329203},
{"learn":[3.566268704],"iteration":671,"passed_time":0.6764634064,"remaining_time":0.3301785674},
{"learn":[3.562564052],"iteration":672,"passed_time":0.6771030942,"remaining_time":0.3289936282},
{"learn":[3.561173586],"iteration":673,"passed_time":0.6777174893,"remaining_time":0.3277980735},
{"learn":[3.559551904],"iteration":674,"passed_time":0.6783333373,"remaining_time":0.3266049402},
{"learn":[3.558593054],"iteration":675,"passed_time":0.6790168121,"remaining_time":0.3254459277},
{"learn":[3.555647008],"iteration":676,"passed_time":0.6796181625,"remaining_time":0.3242491381},
{"learn":[3.553100059],"iteration":677,"passed_time":0.6802438845,"remaining_time":0.3230656796},
{"learn":[3.55085578],"iteration":678,"passed_time":0.6808907467,"remaining_time":0.3218938582},
{"learn":[3.550737965],"iteration":679,"passed_time":0.6815321057,"remaining_time":0.3207209909},
{"learn":[3.549408772],"iteration":680,"passed_time":0.6821222649,"remaining_time":0.3195257012},
{"learn":[3.547390589],"iteration":681,"passed_time":0.6827362079,"remaining_time":0.3183432758},
{"learn":[3.54723575],"iteration":682,"passed_time":0.6833175888,"remaining_time":0.3171474021},
{"learn":[3.543988891],"iteration":683,"passed_time":0.6838786424,"remaining_time":0.3159439342},
{"learn":[3.543868508],"iteration":684,"passed_time":0.6844545614,"remaining_time":0.3147491779},
{"learn":[3.542752124],"iteration":685,"passed_time":0.6850324872,"remaining_time":0.3135571443},
{"learn":[3.541334315],"iteration":686,"passed_time":0.685593288,"remaining_time":0.3123590963},
{"learn":[3.540208266],"iteration":687,"passed_time":0.6861746566,"remaining_time":0.311172228},
{"learn":[3.537730983],"iteration":688,"passed_time":0.6867448524,"remaining_time":0.3099820742},
{"learn":[3.53419867],"iteration":689,"passed_time":0.6873406926,"remaining_time":0.3088052387},
{"learn":[3.532628335],"iteration":690,"passed_time":0.6879474298,"remaining_time":0.3076349577},
{"learn":[3.532204987],"iteration":691,"passed_time":0.6885201849,"remaining_time":0.3064511806},
{"learn":[3.530618147],"iteration":692,"passed_time":0.6891042017,"remaining_time":0.3052741557},
{"learn":[3.528909306],"iteration":693,"passed_time":0.6898092889,"remaining_time":0.3041522225},
{"learn":[3.526700678],"iteration":694,"passed_time":0.6903969217,"remaining_time":0.302979944},
{"learn":[3.526439574],"iteration":695,"passed_time":0.6909408088,"remaining_time":0.3017902383},
{"learn":[3.525784216],"iteration":696,"passed_time":0.6915410871,"remaining_time":0.3006269001},
{"learn":[3.524112693],"iteration":697,"passed_time":0.6921133273,"remaining_time":0.2994530442},
{"learn":[3.522813541],"iteration":698,"passed_time":0.6927052075,"remaining_time":0.2982893669},
{"learn":[3.519148203],"iteration":699,"passed_time":0.6933147208,"remaining_time":0.2971348803},
{"learn":[3.517236747],"iteration":700,"passed_time":0.6938884782,"remaining_time":0.2959666975},
{"learn":[3.515603888],"iteration":701,"passed_time":0.6944674753,"remaining_time":0.2948024325},
{"learn":[3.51263524],"iteration":702,"passed_time":0.695068631,"remaining_time":0.293649194},
{"learn":[3.51123442],"iteration":703,"passed_time":0.6956336515,"remaining_time":0.2924823307},
{"learn":[3.50828027],"iteration":704,"passed_time":0.6962730872,"remaining_time":0.2913483131},
{"learn":[3.508265537],"iteration":705,"passed_time":0.6966152192,"remaining_time":0.2900918902},
{"learn":[3.506774876],"iteration":706,"passed_time":0.6971886142,"remaining_time":0.2889338953},
{"learn":[3.50552068],"iteration":707,"passed_time":0.6977660328,"remaining_time":0.2877792112},
{"learn":[3.501973993],"iteration":708,"passed_time":0.698356585,"remaining_time":0.2866315462},
{"learn":[3.498880354],"iteration":709,"passed_time":0.6989487717,"remaining_time":0.285486118},
{"learn":[3.497370959],"iteration":710,"passed_time":0.6995163132,"remaining_time":0.2843322286},
{"learn":[3.496050455],"iteration":711,"passed_time":0.7001264211,"remaining_time":0.283197204},
{"learn":[3.495630067],"iteration":712,"passed_time":0.7007302832,"remaining_time":0.2820611378},
{"learn":[3.49550669],"iteration":713,"passed_time":0.7013052107,"remaining_time":0.2809149723},
{"learn":[3.493652375],"iteration":714,"passed_time":0.7018882505,"remaining_time":0.2797736383},
{"learn":[3.491915684],"iteration":715,"passed_time":0.702463522,"remaining_time":0.2786307825},
{"learn":[3.490303956],"iteration":716,"passed_time":0.7030487611,"remaining_time":0.277493444},
{"learn":[3.488363853],"iteration":717,"passed_time":0.7036059933,"remaining_time":0.2763466436},
{"learn":[3.485483936],"iteration":718,"passed_time":0.7044061463,"remaining_time":0.2752964216},
{"learn":[3.483763466],"iteration":719,"passed_time":0.7050948141,"remaining_time":0.2742035388},
{"learn":[3.481642352],"iteration":720,"passed_time":0.7057041887,"remaining_time":0.2730810938},
{"learn":[3.479826119],"iteration":721,"passed_time":0.706541965,"remaining_time":0.2720480142},
{"learn":[3.478588728],"iteration":722,"passed_time":0.7071676173,"remaining_time":0.2709342047},
{"learn":[3.475390887],"iteration":723,"passed_time":0.7077560447,"remaining_time":0.2698075529},
{"learn":[3.472636852],"iteration":724,"passed_time":0.7083661296,"remaining_time":0.2686906009},
{"learn":[3.47061883],"iteration":725,"passed_time":0.7089413804,"remaining_time":0.2675618984},
{"learn":[3.46953149],"iteration":726,"passed_time":0.7095153639,"remaining_time":0.2664342425},
{"learn":[3.467217162],"iteration":727,"passed_time":0.7101216259,"remaining_time":0.2653201679},
{"learn":[3.465686216],"iteration":728,"passed_time":0.7107188063,"remaining_time":0.2642041104},
{"learn":[3.462631216],"iteration":729,"passed_time":0.7112959268,"remaining_time":0.2630820551},
{"learn":[3.461451053],"iteration":730,"passed_time":0.7118871411,"remaining_time":0.2619666771},
{"learn":[3.458950469],"iteration":731,"passed_time":0.7125063338,"remaining_time":0.2608629747},
{"learn":[3.458072145],"iteration":732,"passed_time":0.7130608918,"remaining_time":0.2597370506},
{"learn":[3.454364268],"iteration":733,"passed_time":0.7136518961,"remaining_time":0.2586258915},
{"learn":[3.453243406],"iteration":734,"passed_time":0.7142426913,"remaining_time":0.2575160724},
{"learn":[3.453017963],"iteration":735,"passed_time":0.7148491503,"remaining_time":0.2564132822},
{"learn":[3.45201581],"iteration":736,"passed_time":0.7154193399,"remaining_time":0.2552988961},
{"learn":[3.449510107],"iteration":737,"passed_time":0.7159898614,"remaining_time":0.2541861026},
{"learn":[3.447189189],"iteration":738,"passed_time":0.7165756521,"remaining_time":0.2530801694},
{"learn":[3.446423605],"iteration":739,"passed_time":0.7171259904,"remaining_time":0.2519631858},
{"learn":[3.445531987],"iteration":740,"passed_time":0.7177044472,"remaining_time":0.2508575598},
{"learn":[3.445328199],"iteration":741,"passed_time":0.7183902783,"remaining_time":0.2497906898},
{"learn":[3.443327544],"iteration":742,"passed_time":0.7190930705,"remaining_time":0.2487307122},
{"learn":[3.441475798],"iteration":743,"passed_time":0.7197599804,"remaining_time":0.2476593481},
{"learn":[3.439046501],"iteration":744,"passed_time":0.7204230483,"remaining_time":0.2465877548},
{"learn":[3.435899469],"iteration":745,"passed_time":0.721088254,"remaining_time":0.2455179846},
{"learn":[3.433988352],"iteration":746,"passed_time":0.7217460945,"remaining_time":0.2444468031},
{"learn":[3.433413263],"iteration":747,"passed_time":0.7223773802,"remaining_time":0.2433677805},
{"learn":[3.429944699],"iteration":748,"passed_time":0.7229962668,"remaining_time":0.2422857984},
{"learn":[3.429291634],"iteration":749,"passed_time":0.7236582807,"remaining_time":0.2412194269},
{"learn":[3.429175603],"iteration":750,"passed_time":0.7242834302,"remaining_time":0.2401419096},
{"learn":[3.428780323],"iteration":751,"passed_time":0.7249658354,"remaining_time":0.2390844776},
{"learn":[3.423893341],"iteration":752,"passed_time":0.7256363727,"remaining_time":0.2380241488},
{"learn":[3.421024316],"iteration":753,"passed_time":0.7263040209,"remaining_time":0.2369639113},
{"learn":[3.420969872],"iteration":754,"passed_time":0.7269341914,"remaining_time":0.2358925522},
{"learn":[3.419544785],"iteration":755,"passed_time":0.7276295617,"remaining_time":0.2348434035},
{"learn":[3.417057977],"iteration":756,"passed_time":0.7282548185,"remaining_time":0.2337726828},
{"learn":[3.415160245],"iteration":757,"passed_time":0.728911459,"remaining_time":0.2327131571},
{"learn":[3.412854597],"iteration":758,"passed_time":0.7295587392,"remaining_time":0.2316517209},
{"learn":[3.410926347],"iteration":759,"passed_time":0.730220052,"remaining_time":0.2305958059},
{"learn":[3.408963843],"iteration":760,"passed_time":0.7308548311,"remaining_time":0.2295325948},
{"learn":[3.407629634],"iteration":761,"passed_time":0.7314453956,"remaining_time":0.2284566984},
{"learn":[3.404384724],"iteration":762,"passed_time":0.7321016285,"remaining_time":0.2274024718},
{"learn":[3.403041656],"iteration":763,"passed_time":0.7327287113,"remaining_time":0.2263402826},
{"learn":[3.401101731],"iteration":764,"passed_time":0.7334221583,"remaining_time":0.2252996172},
{"learn":[3.400890668],"iteration":765,"passed_time":0.7340559658,"remaining_time":0.2242416397},
{"learn":[3.399289941],"iteration":766,"passed_time":0.7346715888,"remaining_time":0.2231792441},
{"learn":[3.399202366],"iteration":767,"passed_time":0.7353209472,"remaining_time":0.2221282028},
{"learn":[3.397447845],"iteration":768,"passed_time":0.7359915075,"remaining_time":0.2210845751},
{"learn":[3.394655341],"iteration":769,"passed_time":0.7365854589,"remaining_time":0.2200190332},
{"learn":[3.393228229],"iteration":770,"passed_time":0.7372219338,"remaining_time":0.2189673448},
{"learn":[3.389691197],"iteration":771,"passed_time":0.7378581174,"remaining_time":0.2179166461},
{"learn":[3.389626772],"iteration":772,"passed_time":0.738473642,"remaining_time":0.2168609531},
{"learn":[3.388480222],"iteration":773,"passed_time":0.7391135555,"remaining_time":0.2158135188},
{"learn":[3.388215066],"iteration":774,"passed_time":0.7397533609,"remaining_time":0.2147671048},
{"learn":[3.386324358],"iteration":775,"passed_time":0.7403558162,"remaining_time":0.2137109573},
{"learn":[3.383913061],"iteration":776,"passed_time":0.7410006954,"remaining_time":0.2126681532},
{"learn":[3.382839768],"iteration":777,"passed_time":0.7416428,"remaining_time":0.2116255805},
{"learn":[3.381961844],"iteration":778,"passed_time":0.7422307646,"remaining_time":0.2105686765},
{"learn":[3.381521703],"iteration":779,"passed_time":0.742890718,"remaining_time":0.2095332794},
{"learn":[3.380918963],"iteration":780,"passed_time":0.7435196739,"remaining_time":0.2084901518},
{"learn":[3.377139006],"iteration":781,"passed_time":0.7440959293,"remaining_time":0.2074333921},
{"learn":[3.376004372],"iteration":782,"passed_time":0.7446859237,"remaining_time":0.2063816672},
{"learn":[3.373826468],"iteration":783,"passed_time":0.7452767916,"remaining_time":0.205331361},
{"learn":[3.373546786],"iteration":784,"passed_time":0.7458398835,"remaining_time":0.2042746178},
{"learn":[3.372109181],"iteration":785,"passed_time":0.7464664514,"remaining_time":0.203236413},
{"learn":[3.370764924],"iteration":786,"passed_time":0.7470837637,"remaining_time":0.2021967493},
{"learn":[3.367833107],"iteration":787,"passed_time":0.7481306772,"remaining_time":0.2012737355},
{"learn":[3.36450404],"iteration":788,"passed_time":0.7488161903,"remaining_time":0.2002537594},
{"learn":[3.361794558],"iteration":789,"passed_time":0.7494675696,"remaining_time":0.1992255565},
{"learn":[3.356880529],"iteration":790,"passed_time":0.7501145936,"remaining_time":0.1981971556},
{"learn":[3.353843509],"iteration":791,"passed_time":0.7507161064,"remaining_time":0.1971577653},
{"learn":[3.353640253],"iteration":792,"passed_time":0.7513122224,"remaining_time":0.1961180707},
{"learn":[3.353055088],"iteration":793,"passed_time":0.7518869568,"remaining_time":0.195073946},
{"learn":[3.351415617],"iteration":794,"passed_time":0.7524594299,"remaining_time":0.194030419},
{"learn":[3.349169061],"iteration":795,"passed_time":0.7530509492,"remaining_time":0.1929929568},
{"learn":[3.346211014],"iteration":796,"passed_time":0.7536189083,"remaining_time":0.1919506128},
{"learn":[3.344560452],"iteration":797,"passed_time":0.754180204,"remaining_time":0.1909077709},
{"learn":[3.344445461],"iteration":798,"passed_time":0.7547829888,"remaining_time":0.1898765717},
{"learn":[3.342608898],"iteration":799,"passed_time":0.7553945342,"remaining_time":0.1888486336},
{"learn":[3.339572899],"iteration":800,"passed_time":0.755981377,"remaining_time":0.187815598},
{"learn":[3.339309302],"iteration":801,"passed_time":0.7565468734,"remaining_time":0.1867784051},
{"learn":[3.33698088],"iteration":802,"passed_time":0.7571753707,"remaining_time":0.1857578431},
{"learn":[3.334746342],"iteration":803,"passed_time":0.7577803585,"remaining_time":0.1847325252},
{"learn":[3.332048511],"iteration":804,"passed_time":0.7583815709,"remaining_time":0.1837073371},
{"learn":[3.331932544],"iteration":805,"passed_time":0.7589481086,"remaining_time":0.1826748549},
{"learn":[3.330541133],"iteration":806,"passed_time":0.7594973802,"remaining_time":0.1816393982},
{"learn":[3.329124989],"iteration":807,"passed_time":0.7600959039,"remaining_time":0.1806168484},
{"learn":[3.32583918],"iteration":808,"passed_time":0.7606583543,"remaining_time":0.1795868303},
{"learn":[3.325287299],"iteration":809,"passed_time":0.7612198041,"remaining_time":0.1785577318},
{"learn":[3.322745162],"iteration":810,"passed_time":0.7618507627,"remaining_time":0.1775459854},
{"learn":[3.319733662],"iteration":811,"passed_time":0.7625012723,"remaining_time":0.1765397034},
{"learn":[3.318080007],"iteration":812,"passed_time":0.7630907434,"remaining_time":0.1755202571},
{"learn":[3.317179538],"iteration":813,"passed_time":0.7636739947,"remaining_time":0.174500446},
{"learn":[3.315685949],"iteration":814,"passed_time":0.7642757811,"remaining_time":0.1734859135},
{"learn":[3.314944576],"iteration":815,"passed_time":0.7648584293,"remaining_time":0.1724680772},
{"learn":[3.312369052],"iteration":816,"passed_time":0.7654597559,"remaining_time":0.17145549},
{"learn":[3.312321621],"iteration":817,"passed_time":0.7658991668,"remaining_time":0.1704078831},
{"learn":[3.309465776],"iteration":818,"passed_time":0.7664723602,"remaining_time":0.1693913275},
{"learn":[3.308307377],"iteration":819,"passed_time":0.7670393301,"remaining_time":0.1683744871},
{"learn":[3.308076804],"iteration":820,"passed_time":0.7675937318,"remaining_time":0.1673560024},
{"learn":[3.305643326],"iteration":821,"passed_time":0.7682011409,"remaining_time":0.1663501254},
{"learn":[3.304154814],"iteration":822,"passed_time":0.7687743275,"remaining_time":0.1653378566},
{"learn":[3.303076321],"iteration":823,"passed_time":0.7693469753,"remaining_time":0.1643265384},
{"learn":[3.301746372],"iteration":824,"passed_time":0.7699343016,"remaining_time":0.1633193973},
{"learn":[3.301345455],"iteration":825,"passed_time":0.7704853678,"remaining_time":0.1623056344},
{"learn":[3.299181039],"iteration":826,"passed_time":0.7710503822,"remaining_time":0.1612959082},
{"learn":[3.297989357],"iteration":827,"passed_time":0.771668371,"remaining_time":0.1602982607},
{"learn":[3.294775182],"iteration":828,"passed_time":0.7722504477,"remaining_time":0.1592941213},
{"learn":[3.293840636],"iteration":829,"passed_time":0.7728826438,"remaining_time":0.1583012644},
{"learn":[3.289279397],"iteration":830,"passed_time":0.7734520465,"remaining_time":0.1572965053},
{"learn":[3.286204979],"iteration":831,"passed_time":0.7740673206,"remaining_time":0.1563020551},
{"learn":[3.284833593],"iteration":832,"passed_time":0.7746219943,"remaining_time":0.1552963662},
{"learn":[3.283519914],"iteration":833,"passed_time":0.7752008358,"remaining_time":0.1542965692},
{"learn":[3.282853026],"iteration":834,"passed_time":0.7757810022,"remaining_time":0.1532980423},
{"learn":[3.281944673],"iteration":835,"passed_time":0.7766331765,"remaining_time":0.1523538767},
{"learn":[3.279764865],"iteration":836,"passed_time":0.7773582683,"remaining_time":0.1513851825},
{"learn":[3.277468839],"iteration":837,"passed_time":0.7783080256,"remaining_time":0.1504605014},
{"learn":[3.277124974],"iteration":838,"passed_time":0.7789813821,"remaining_time":0.1494827205},
{"learn":[3.275636037],"iteration":839,"passed_time":0.7796506191,"remaining_time":0.1485048798},
{"learn":[3.274413635],"iteration":840,"passed_time":0.7803062634,"remaining_time":0.1475252032},
{"learn":[3.272636087],"iteration":841,"passed_time":0.7809519594,"remaining_time":0.1465444294},
{"learn":[3.269644466],"iteration":842,"passed_time":0.7815380444,"remaining_time":0.1455533487},
{"learn":[3.26852083],"iteration":843,"passed_time":0.7822204557,"remaining_time":0.1445810321},
{"learn":[3.267820927],"iteration":844,"passed_time":0.7828451263,"remaining_time":0.1435988102},
{"learn":[3.267331099],"iteration":845,"passed_time":0.7834125989,"remaining_time":0.1426070215},
{"learn":[3.267231014],"iteration":846,"passed_time":0.7840026944,"remaining_time":0.1416203214},
{"learn":[3.267158695],"iteration":847,"passed_time":0.7845467233,"remaining_time":0.1406262995},
{"learn":[3.264718705],"iteration":848,"passed_time":0.7851181214,"remaining_time":0.1396382053},
{"learn":[3.261678512],"iteration":849,"passed_time":0.7856772976,"remaining_time":0.1386489349},
{"learn":[3.261368381],"iteration":850,"passed_time":0.786277553,"remaining_time":0.1376678677},
{"learn":[3.260128799],"iteration":851,"passed_time":0.7868528146,"remaining_time":0.1366833528},
{"learn":[3.258972952],"iteration":852,"passed_time":0.7874271443,"remaining_time":0.1356996368},
{"learn":[3.258724846],"iteration":853,"passed_time":0.7880012634,"remaining_time":0.1347168436},
{"learn":[3.25686724],"iteration":854,"passed_time":0.7885759257,"remaining_time":0.1337350985},
{"learn":[3.255750259],"iteration":855,"passed_time":0.7891544017,"remaining_time":0.1327549461},
{"learn":[3.254915866],"iteration":856,"passed_time":0.7897502312,"remaining_time":0.1317786267},
{"learn":[3.254348625],"iteration":857,"passed_time":0.7903094987,"remaining_time":0.1307971431},
{"learn":[3.253408514],"iteration":858,"passed_time":0.7909647507,"remaining_time":0.129832398},
{"learn":[3.253291714],"iteration":859,"passed_time":0.7915589534,"remaining_time":0.1288584343},
{"learn":[3.250186342],"iteration":860,"passed_time":0.7922160643,"remaining_time":0.1278955086},
{"learn":[3.249141318],"iteration":861,"passed_time":0.7928253868,"remaining_time":0.126925642},
{"learn":[3.246300388],"iteration":862,"passed_time":0.7934020775,"remaining_time":0.1259514306},
{"learn":[3.245205135],"iteration":863,"passed_time":0.7939931592,"remaining_time":0.1249804047},
{"learn":[3.244403535],"iteration":864,"passed_time":0.7945526672,"remaining_time":0.1240053296},
{"learn":[3.244211781],"iteration":865,"passed_time":0.7951360082,"remaining_time":0.123034902},
{"learn":[3.242286347],"iteration":866,"passed_time":0.7957069389,"remaining_time":0.1220634635},
{"learn":[3.239606746],"iteration":867,"passed_time":0.7963034304,"remaining_time":0.121096835},
{"learn":[3.236773361],"iteration":868,"passed_time":0.7968980453,"remaining_time":0.1201307755},
{"learn":[3.234552446],"iteration":869,"passed_time":0.7974478158,"remaining_time":0.119158869},
{"learn":[3.233724647],"iteration":870,"passed_time":0.7980478903,"remaining_time":0.1181953821},
{"learn":[3.230851485],"iteration":871,"passed_time":0.7986372227,"remaining_time":0.117231152},
{"learn":[3.227728941],"iteration":872,"passed_time":0.7992360773,"remaining_time":0.1162691659},
{"learn":[3.225787575],"iteration":873,"passed_time":0.7998469975,"remaining_time":0.1153097502},
{"learn":[3.222797487],"iteration":874,"passed_time":0.8004364976,"remaining_time":0.1143480711},
{"learn":[3.22137014],"iteration":875,"passed_time":0.8010217443,"remaining_time":0.1133866396},
{"learn":[3.219701963],"iteration":876,"passed_time":0.8015853472,"remaining_time":0.1124230305},
{"learn":[3.21783327],"iteration":877,"passed_time":0.8021760282,"remaining_time":0.111464095},
{"learn":[3.217713355],"iteration":878,"passed_time":0.8027203605,"remaining_time":0.1104996173},
{"learn":[3.217666091],"iteration":879,"passed_time":0.8032395526,"remaining_time":0.1095326663},
{"learn":[3.214962005],"iteration":880,"passed_time":0.8038253142,"remaining_time":0.1085757235},
{"learn":[3.214081828],"iteration":881,"passed_time":0.8043760302,"remaining_time":0.1076149338},
{"learn":[3.213358337],"iteration":882,"passed_time":0.8049609896,"remaining_time":0.1066596102},
{"learn":[3.210850401],"iteration":883,"passed_time":0.8055880578,"remaining_time":0.1057106501},
{"learn":[3.207810328],"iteration":884,"passed_time":0.8061787534,"remaining_time":0.1047576911},
{"learn":[3.204935073],"iteration":885,"passed_time":0.8068163201,"remaining_time":0.1038115807},
{"learn":[3.20280198],"iteration":886,"passed_time":0.8075223663,"remaining_time":0.10287489},
{"learn":[3.200663495],"iteration":887,"passed_time":0.8082483612,"remaining_time":0.1019412347},
{"learn":[3.197301669],"iteration":888,"passed_time":0.8090290436,"remaining_time":0.101014875},
{"learn":[3.195666943],"iteration":889,"passed_time":0.8097410271,"remaining_time":0.1000803517},
{"learn":[3.193886506],"iteration":890,"passed_time":0.8104933641,"remaining_time":0.09915126451},
{"learn":[3.190601248],"iteration":891,"passed_time":0.8111678668,"remaining_time":0.09821314979},
{"learn":[3.188983797],"iteration":892,"passed_time":0.8118806549,"remaining_time":0.09728021284},
{"learn":[3.187365749],"iteration":893,"passed_time":0.8126092915,"remaining_time":0.09634964753},
{"learn":[3.186160771],"iteration":894,"passed_time":0.8133147786,"remaining_time":0.0954168176},
{"learn":[3.185358981],"iteration":895,"passed_time":0.8140032916,"remaining_time":0.09448252492},
{"learn":[3.183832164],"iteration":896,"passed_time":0.8147571879,"remaining_time":0.09355628802},
{"learn":[3.183106966],"iteration":897,"passed_time":0.8155394162,"remaining_time":0.09263365307},
{"learn":[3.182838152],"iteration":898,"passed_time":0.8162659537,"remaining_time":0.09170507377},
{"learn":[3.180835453],"iteration":899,"passed_time":0.8170534596,"remaining_time":0.09078371773},
{"learn":[3.179957348],"iteration":900,"passed_time":0.8177750236,"remaining_time":0.08985541325},
{"learn":[3.179752966],"iteration":901,"passed_time":0.8185284268,"remaining_time":0.08893102642},
{"learn":[3.178851983],"iteration":902,"passed_time":0.8191871144,"remaining_time":0.08799684396},
{"learn":[3.176748586],"iteration":903,"passed_time":0.8199228212,"remaining_time":0.08707145004},
{"learn":[3.172960988],"iteration":904,"passed_time":0.8206561887,"remaining_time":0.08614622975},
{"learn":[3.172794225],"iteration":905,"passed_time":0.8213669075,"remaining_time":0.08521908312},
{"learn":[3.169996507],"iteration":906,"passed_time":0.8222257076,"remaining_time":0.08430759736},
{"learn":[3.16813015],"iteration":907,"passed_time":0.8230047452,"remaining_time":0.08338814599},
{"learn":[3.166920871],"iteration":908,"passed_time":0.8237549845,"remaining_time":0.08246612056},
{"learn":[3.16531606],"iteration":909,"passed_time":0.8245398453,"remaining_time":0.08154789679},
{"learn":[3.162035247],"iteration":910,"passed_time":0.8251780539,"remaining_time":0.08061563863},
{"learn":[3.16189467],"iteration":911,"passed_time":0.8258700009,"remaining_time":0.07968921061},
{"learn":[3.161008416],"iteration":912,"passed_time":0.8265325408,"remaining_time":0.07876049403},
{"learn":[3.160560787],"iteration":913,"passed_time":0.8272060393,"remaining_time":0.07783339101},
{"learn":[3.160416261],"iteration":914,"passed_time":0.8279283121,"remaining_time":0.07691137326},
{"learn":[3.15844291],"iteration":915,"passed_time":0.8286748501,"remaining_time":0.07599201682},
{"learn":[3.155040501],"iteration":916,"passed_time":0.8293578088,"remaining_time":0.07506728259},
{"learn":[3.154937548],"iteration":917,"passed_time":0.8300446418,"remaining_time":0.07414342117},
{"learn":[3.153721161],"iteration":918,"passed_time":0.8306826369,"remaining_time":0.07321577105},
{"learn":[3.153170511],"iteration":919,"passed_time":0.8313513943,"remaining_time":0.07229142559},
{"learn":[3.153113601],"iteration":920,"passed_time":0.8319545764,"remaining_time":0.07136201035},
{"learn":[3.150607379],"iteration":921,"passed_time":0.8326549825,"remaining_time":0.0704415278},
{"learn":[3.148408359],"iteration":922,"passed_time":0.833370821,"remaining_time":0.06952280955},
{"learn":[3.147495728],"iteration":923,"passed_time":0.8342203333,"remaining_time":0.06861552525},
{"learn":[3.146946235],"iteration":924,"passed_time":0.835133747,"remaining_time":0.06771354705},
{"learn":[3.14472738],"iteration":925,"passed_time":0.8358805945,"remaining_time":0.06679823325},
{"learn":[3.144469477],"iteration":926,"passed_time":0.836741475,"remaining_time":0.06589226286},
{"learn":[3.142975516],"iteration":927,"passed_time":0.8374887474,"remaining_time":0.06497757523},
{"learn":[3.14079113],"iteration":928,"passed_time":0.8382503737,"remaining_time":0.06406434503},
{"learn":[3.138173032],"iteration":929,"passed_time":0.8391963882,"remaining_time":0.06316531954},
{"learn":[3.136352813],"iteration":930,"passed_time":0.8400502459,"remaining_time":0.06225936302},
{"learn":[3.133735004],"iteration":931,"passed_time":0.8407818564,"remaining_time":0.06134459896},
{"learn":[3.1319496],"iteration":932,"passed_time":0.8416168328,"remaining_time":0.06043765037},
{"learn":[3.129865343],"iteration":933,"passed_time":0.8423110682,"remaining_time":0.0595209106},
{"learn":[3.129830206],"iteration":934,"passed_time":0.8428574192,"remaining_time":0.05859436604},
{"learn":[3.126676562],"iteration":935,"passed_time":0.8435485409,"remaining_time":0.05767853271},
{"learn":[3.12645665],"iteration":936,"passed_time":0.8441826228,"remaining_time":0.0567593439},
{"learn":[3.126378007],"iteration":937,"passed_time":0.8448973801,"remaining_time":0.05584609549},
{"learn":[3.124621914],"iteration":938,"passed_time":0.8456645411,"remaining_time":0.05493667413},
{"learn":[3.123379018],"iteration":939,"passed_time":0.8464005031,"remaining_time":0.05402556403},
{"learn":[3.123332451],"iteration":940,"passed_time":0.8470961029,"remaining_time":0.05311229551},
{"learn":[3.122432444],"iteration":941,"passed_time":0.8478327664,"remaining_time":0.05220201747},
{"learn":[3.121889006],"iteration":942,"passed_time":0.8485132241,"remaining_time":0.05128871026},
{"learn":[3.121070914],"iteration":943,"passed_time":0.8491111574,"remaining_time":0.05037100086},
{"learn":[3.118444705],"iteration":944,"passed_time":0.8497770577,"remaining_time":0.04945792399},
{"learn":[3.116820458],"iteration":945,"passed_time":0.8505826508,"remaining_time":0.0485533437},
{"learn":[3.114971041],"iteration":946,"passed_time":0.8513211832,"remaining_time":0.04764521933},
{"learn":[3.114685138],"iteration":947,"passed_time":0.8520385707,"remaining_time":0.04673629291},
{"learn":[3.113399363],"iteration":948,"passed_time":0.8527351762,"remaining_time":0.0458266533},
{"learn":[3.110575399],"iteration":949,"passed_time":0.8534776096,"remaining_time":0.04491987419},
{"learn":[3.110466553],"iteration":950,"passed_time":0.854177225,"remaining_time":0.04401123451},
{"learn":[3.108691641],"iteration":951,"passed_time":0.8548566931,"remaining_time":0.04310201814},
{"learn":[3.107898017],"iteration":952,"passed_time":0.8555749503,"remaining_time":0.04219519692},
{"learn":[3.105551729],"iteration":953,"passed_time":0.8562107601,"remaining_time":0.04128479556},
{"learn":[3.104824945],"iteration":954,"passed_time":0.8568821648,"remaining_time":0.04037664651},
{"learn":[3.103186704],"iteration":955,"passed_time":0.857639415,"remaining_time":0.03947294379},
{"learn":[3.102330655],"iteration":956,"passed_time":0.8584484827,"remaining_time":0.0385718754},
{"learn":[3.102291298],"iteration":957,"passed_time":0.8592234576,"remaining_time":0.0376695044},
{"learn":[3.100363529],"iteration":958,"passed_time":0.8599543508,"remaining_time":0.03676551448},
{"learn":[3.097871596],"iteration":959,"passed_time":0.8605609975,"remaining_time":0.03585670823},
{"learn":[3.097372213],"iteration":960,"passed_time":0.8611335557,"remaining_time":0.03494714742},
{"learn":[3.095981813],"iteration":961,"passed_time":0.8617598095,"remaining_time":0.03404040827},
{"learn":[3.095347452],"iteration":962,"passed_time":0.8623191574,"remaining_time":0.03313168102},
{"learn":[3.094728409],"iteration":963,"passed_time":0.8628722986,"remaining_time":0.03222344684},
{"learn":[3.094118537],"iteration":964,"passed_time":0.8634786649,"remaining_time":0.03131787904},
{"learn":[3.093793695],"iteration":965,"passed_time":0.8640281641,"remaining_time":0.03041092917},
{"learn":[3.092581602],"iteration":966,"passed_time":0.8646035865,"remaining_time":0.02950560326},
{"learn":[3.091694202],"iteration":967,"passed_time":0.865320222,"remaining_time":0.02860562717},
{"learn":[3.090298312],"iteration":968,"passed_time":0.866160543,"remaining_time":0.02770998641},
{"learn":[3.090020107],"iteration":969,"passed_time":0.8667738478,"remaining_time":0.02680743859},
{"learn":[3.088949869],"iteration":970,"passed_time":0.8673658199,"remaining_time":0.02590484941},
{"learn":[3.086700204],"iteration":971,"passed_time":0.8679599958,"remaining_time":0.02500296284},
{"learn":[3.086584317],"iteration":972,"passed_time":0.8685125906,"remaining_time":0.02410055493},
{"learn":[3.084850742],"iteration":973,"passed_time":0.8690740618,"remaining_time":0.02319910227},
{"learn":[3.084239948],"iteration":974,"passed_time":0.8696427634,"remaining_time":0.0222985324},
{"learn":[3.082561673],"iteration":975,"passed_time":0.8702491458,"remaining_time":0.02139956916},
{"learn":[3.07991814],"iteration":976,"passed_time":0.8708075167,"remaining_time":0.0205000746},
{"learn":[3.079350277],"iteration":977,"passed_time":0.8714944118,"remaining_time":0.01960416877},
{"learn":[3.077637462],"iteration":978,"passed_time":0.8722619168,"remaining_time":0.01871041905},
{"learn":[3.076733301],"iteration":979,"passed_time":0.8728844642,"remaining_time":0.01781396866},
{"learn":[3.07594065],"iteration":980,"passed_time":0.8735109072,"remaining_time":0.01691815213},
{"learn":[3.072594655],"iteration":981,"passed_time":0.8740967332,"remaining_time":0.01602213971},
{"learn":[3.071977674],"iteration":982,"passed_time":0.8747104601,"remaining_time":0.01512724092},
{"learn":[3.069532634],"iteration":983,"passed_time":0.875297342,"remaining_time":0.01423247711},
{"learn":[3.068870784],"iteration":984,"passed_time":0.8758871578,"remaining_time":0.01333838311},
{"learn":[3.068801463],"iteration":985,"passed_time":0.8764326449,"remaining_time":0.01244427691},
{"learn":[3.067433249],"iteration":986,"passed_time":0.8770065111,"remaining_time":0.01155125091},
{"learn":[3.065611456],"iteration":987,"passed_time":0.8775748917,"remaining_time":0.01065880435},
{"learn":[3.063039162],"iteration":988,"passed_time":0.8783956838,"remaining_time":0.009769820548},
{"learn":[3.06177873],"iteration":989,"passed_time":0.8790542948,"remaining_time":0.008879336311},
{"learn":[3.061689148],"iteration":990,"passed_time":0.8796799171,"remaining_time":0.007989020438},
{"learn":[3.058984039],"iteration":991,"passed_time":0.8803100014,"remaining_time":0.007099274205},
{"learn":[3.057492984],"iteration":992,"passed_time":0.8809235988,"remaining_time":0.006209934735},
{"learn":[3.057290731],"iteration":993,"passed_time":0.8814763523,"remaining_time":0.005320782811},
{"learn":[3.056068348],"iteration":994,"passed_time":0.8820550222,"remaining_time":0.004432437297},
{"learn":[3.054987307],"iteration":995,"passed_time":0.882633915,"remaining_time":0.003544714518},
{"learn":[3.054200234],"iteration":996,"passed_time":0.8831922745,"remaining_time":0.002657549472},
{"learn":[3.052732869],"iteration":997,"passed_time":0.8837386979,"remaining_time":0.001771019435},
{"learn":[3.051787862],"iteration":998,"passed_time":0.884384346,"remaining_time":0.0008852696156},
{"learn":[3.051366222],"iteration":999,"passed_time":0.8851181372,"remaining_time":0}
]}